Workbook

Sheet 1
I4: KEMENTRIAN KEUANGAN | Y4: SPT TAHUNAN | AP4: INDUK
I5: REPUBLIK INDONESIA | Y5: PAJAK PENGHASILAN (PPh) | AP5: HALAMAN 1
I6: DIREKTORAT JENDERAL PAJAK | Y6: WAJIB PAJAK ORANG PRIBADI
E9: TAHUN PAJAK/BAGIAN TAHUN PAJAK | O9: PERIODE | V9: STATUS | AC9: SUMBER PENGHASILAN | AK9: METODE PEMBUKUAN
G10: TAHUN PAJAK | O10: BULAN MULAI | R10: BULAN AKHIR | X10: NORMAL | AE10: PEKERJAAN | AM10: PEMBUKUAN STELSEL AKRUAL
G12: BAGIAN TAHUN PAJAK | X12: PEMBETULAN | AE12: KEGIATAN USAHA | AM12: PEMBUKUAN STELSEL KAS
Q14: S.D | AE14: PEKERJAAN BEBAS | AM14: PENCATATAN
D18: A. | E18: IDENTITAS WAJIB PAJAK
E21: 1. | F21: NIK/NPWP | AB21: 7. | AC21: STATUS KEWAJIBAN PERPAJAKAN SUAMI DAN ISTRI
E23: 2. | F23: NAMA | AD23: PISAH HARTA | AK23: MEMILIH TERPISAH
E25: 3. | F25: JENIS ID | K25: KTP | O25: KITAS | S25: PASPOR | AC25: (Jika status kewajiban perpajakan Anda dengan pasangan adalah PH atau MT, Anda diwajibkan mengisi bagian ini dan Lampiran 4 Bagian B)
E27: 4. | F27: NO. ID
E29: 5. | F29: NO. TELEPON | AB29: 8. | AC29: NIK/NPWP SUAMI/ISTRI*
E31: 6. | F31: EMAIL
D34: B. | E34: IKHTISAR PENGHASILAN NETO
E36: 1 | F36: a | G36: APAKAH ANDA MENERIMA PENGHASILAN DALAM NEGERI DARI PEKERJAAN ? | AL36: ='L1-3'!AJ36 -> 0
I37: Tidak. (Lanjut ke pertanyaan selanjutnya)
I38: Ya. (Isi Lampiran 1 Bagian D lalu ke pertanyaan selanjutnya)
F40: b | G40: 1) | H40: APAKAH ANDA MENERIMA PENGHASILAN DALAM NEGERI DARI USAHA DAN/ATAU PEKERJAAN BEBAS ?
I41: Tidak. (Lanjut ke pertanyaan 1c)
I42: Ya. (Lanjut ke pertanyaan selanjutnya)
G44: 2) | H44: APAKAH ANDA TERMASUK WAJIB PAJAK ORANG PRIBADI YANG MEMILIKI PEREDARAN BRUTO TERTENTU ATAU ORANG PRIBADI PENGUSAHA TERTENTU (OPPT) ?
I46: Tidak. (Lanjut ke pertanyaan selanjutnya)
I47: Ya, saya termasuk Wajib Pajak Orang Pribadi yang memiliki Peredaran Bruto Tertentu yang dikenai Pajak bersifat Final. (Isi Lampiran 3B Bagian A. lalu ke pertanyaan selanjutnya)
I49: Ya, saya termasuk Wajib Pajak OPPT. (Isi Lampiran 3B Bagian B, lalu ke pertanyaan selanjutnya)
G51: 3) | H51: APAKAH ANDA MENGGUNAKAN NORMA DALAM MENGHITUNG PENGHASILAN NETO ?
I52: Tidak, saya menyelenggarakan pembukuan (Lanjut ke pertanyaan selanjutnya)
I53: Tidak, saya hanya menerima penghasilan dari usaha yang dikenakan pajak bersifat final dan tidak menyelenggarakan pembukuan. (Lanjut ke pertanyaan 1c)
I55: Ya, saya berhak menggunakan Norma Penghitungan Penghasilan Neto.
I56: (Isi Lampiran 3B Bagian C, Lampiran 3A-4 Bagian A, lalu ke pertanyaan 1c)
G58: 4) | H58: ANDA MENYELENGGARAKAN PEMBUKUAN. SEBUTKAN SEKTOR USAHA YANG ANDA LAKUKAN.
I59: Dagang. (Isi Lampiran 3A-1, lalu ke pertanyaan selanjutnya)
I60: Jasa. (Isi Lampiran 3A-2, lalu ke pertanyaan selanjutnya)
I61: Industri. (Isi Lampiran 3A-3, lalu ke pertanyaan selanjutnya)
G63: 5) | H63: PENGHASILAN NETO DARI USAHA DAN/ATAU PEKERJAAN BEBAS | AL63: ='L3A-4'!AJ27 -> 0
F65: c | G65: APAKAH ANDA MENERIMA PENGHASILAN DALAM NEGERI LAINNYA ? | AL65: ='L3A-4'!AE54 -> 0
I66: Tidak. (Lanjut ke pertanyaan selanjutnya).
I67: Ya. (Isi Lampiran 3A-4 Bagian B lalu ke pertanyaan selanjutnya)
F69: d | G69: APAKAH ANDA MENERIMA PENGHASILAN LUAR NEGERI ? | AL69: ='L2'!T73 -> 0
I70: Tidak. (Lanjut ke pertanyaan selanjutnya).
I71: Ya. (Isi Lampiran 2 Bagian C lalu ke pertanyaan selanjutnya)
D73: C. | E73: PENGHITUNGAN PPh TERUTANG
E75: 2 | F75: PENGHASILAN NETO SETAHUN | X75: ( | Y75: 1a | Z75: + | AA75: 1b | AB75: + | AC75: 1c | AD75: + | AE75: 1d | AF75: ) | AL75: =AL36+AL63+AL65+AL69 -> 0
E77: 3 | F77: APAKAH TERDAPAT PENGURANG PENGHASILAN NETO SEPERTI KOMPENSASI KERUGIAN ATAU ZAKAT/SUMBANGAN KEAGAMAAN YANG BERSIFAT WAJIB YANG DIBAYAR SELAIN YANG TELAH DIPERHITUNGKAN DALAM FORMULIR BPA1 DAN/ATAU BPA2 ? | AL77: ='L5'!R44 -> 0
H79: Tidak. (Lanjut ke pertanyaan selanjutnya).
H80: Ya. (Isi Lampiran 5 Bagian A dan/atau Bagian B, lalu ke pertanyaan selanjutnya)
E82: 4 | F82: PENGHASILAN NETO SETELAH PENGURANG PENGHASILAN NETO | X82: ( | Y82: 2 | Z82: - | AA82: 3 | AB82: ) | AL82: =AL75-AL77 -> 0
AX83: - | AY83: 0
E84: 5 | F84: PENGHASILAN TIDAK KENA PAJAK | X84: - | AL84: =VLOOKUP(X84,AX83:AY95,2,FALSE()) -> 0 | AX84: TK/0 | AY84: 54000000
AX85: TK/1 | AY85: 58500000
E86: 6 | F86: PENGHASILAN KENA PAJAK | X86: ( | Y86: 4 | Z86: - | AA86: 5 | AB86: ) | AL86: =AL82-AL84 -> 0 | AX86: TK/2 | AY86: 63000000
AX87: TK/3 | AY87: 67500000
E88: 7 | F88: PPh TERUTANG | AL88: =(5%*60000000)+(15%*190000000)+(25%*17000000) -> 35750000 | AX88: K/0 | AY88: 58500000
AX89: K/1 | AY89: 63000000
E90: 8 | F90: APAKAH TERDAPAT PENGURANG PPh TERUTANG ? | AX90: K/2 | AY90: 67500000
H91: Tidak. (Lanjut ke pertanyaan selanjutnya). | AX91: K/3 | AY91: 72000000
H92: Ya. (Isi Lampiran 5 Bagian C, lalu ke pertanyaan selanjutnya) | AX92: K/I/0 | AY92: 112500000
AX93: K/I/1 | AY93: 117000000
E94: 9 | F94: PPh TERUTANG SETELAH PENGURANG PPh TERUTANG | X94: ( | Y94: 7 | Z94: - | AA94: 8 | AB94: ) | AL94: =AL88-AL90 -> 35750000 | AX94: K/I/2 | AY94: 121500000
AX95: K/I/3 | AY95: 126000000
D96: D. | E96: KREDIT PAJAK
E98: 10 | F98: a | G98: APAKAH TERDAPAT PPh YANG TELAH DIPOTONG/DIPUNGUT OLEH PIHAK LAIN | AL98: ='L1-3'!AM73 -> 0
I99: Tidak. (Lanjut ke pertanyaan selanjutnya).
I100: Ya. (Isi Lampiran 1 Bagian E, lalu ke pertanyaan selanjutnya)
F102: b | G102: ANGSURAN PPh PASAL 25 | AL102: 11000000
F104: c | G104: STP PPh PASAL 25 (HANYA POKOK PAJAK) | AL104: 1000000
F106: d | G106: APAKAH ANDA MENERIMA PENGEMBALIAN/PENGURANGAN KREDIT PPh LUAR NEGERI YANG TELAH DIKREDITKAN ?
I107: Tidak. (Lanjut ke pertanyaan selanjutnya).
I108: Ya. (Isi dengan jumlah pengembalian/pengurangan kredit PPh luar negeri)

Sheet 2
I4: KEMENTRIAN KEUANGAN | Y4: SPT TAHUNAN | AP4: INDUK
I5: REPUBLIK INDONESIA | Y5: PAJAK PENGHASILAN (PPh) | AP5: HALAMAN 2
I6: DIREKTORAT JENDERAL PAJAK | Y6: WAJIB PAJAK ORANG PRIBADI
D9: E. | E9: PPh KURANG /LEBIH BAYAR
E11: 11 | F11: a | G11: PPh KURANG/LEBIH BAYAR | X11: ( | Y11: 9 | Z11: - | AA11: 10a | AB11: - | AC11: 10b | AD11: - | AE11: 10c | AF11: + | AG11: 10d | AH11: ) | AL11: ='1'!AL94-'1'!AL98-'1'!AL102-'1'!AL104+'1'!AL106 -> 23750000
F13: b | G13: APAKAH TERDAPAT SURAT KEPUTUSAN PERSETUJUAN PENGANGSURAN ATAU PENUNDAAN PEMBAYARAN PAJAK ?
I14: Tidak, saya tidak memilikinya. (Lanjut ke pertanyaan selanjutnya).
I15: Ya, saya memilikinya. (Isi dengan jumlah yang telah disetujui untuk diangsur/ditunda, lalu kepertanyaan selanjutnya)
F17: c | G17: PPh YANG MASIH HARUS DIBAYAR | X17: ( | Y17: 11a | Z17: - | AA17: 11b | AB17: ) | AL17: =AL11-AL13 -> 23750000
D19: F. | E19: PEMBETULAN (DIISI JIKA STATUS SPT ADALAH PEMBETULAN)
E21: 12 | F21: a | G21: PPH KURANG /LEBIH BAYAR PADA SPT YANG DIBETULKAN | Z21: GANTI SPT SEBELUMNYA
F23: b | G23: PPH KURANG /LEBIH BAYAR KARENA PEMBETULAN | X23: ( | Y23: 11a | Z23: - | AA23: 12a | AB23: ) | AL23: 0
D25: G. | E25: PERMOHONAN PENGEMBALIAN PPh LEBIH BAYAR (DIISI JIKA STATUS SPT ADALAH LEBIH BAYAR)
E27: PPh LEBIH BAYAR PADA 11a ATAU 12b MOHON : | V27: NOMOR REKENING | AK27: NAMA BANK
G29: Dikembalikan melalui pemeriksaan.
G30: Dikembalikan melalui permhonan pengembalian pendahuluan | V30: NAMA PEMILIK REKENING
D32: H. | E32: ANGSURAN PPh PASAL 25 TAHUN PAJAK BERIKUTNYA
E34: 13 | F34: a | G34: APAKAH ANDA HANYA MENERIMA PENGHASILAN TERATUR DAN BERKEWAJIBAN MEMBAYAR ANGSURAN PPh PASAL 25 TAHUN PAJAK BERIKUTNYA ? | AL34: =(1/Y37*('1'!AL94-'1'!AL98)) -> 2979166.7
I36: Tidak. (Lanjut ke pertanyaan selanjutnya).
I37: Ya, angsuran PPh Pasal 25-nya adalah | X37: (1/ | Y37: 12 | Z37: X | AA37: ( | AB37: 9 | AC37: - | AD37: 10a | AE37: )
F39: b | G39: APAKAH ANDA MENYUSUN PERHITUNGAN TERSENDIRI ANGUSRAN PPh PASAL 25 TAHUN PAJAK BERIKUTNYA ?
I40: Tidak. (Lanjut ke pertanyaan selanjutnya).
I41: Ya. (Isi Lampiran 4 Bagian A)
F43: c | G43: APAKAH ANDA MEMBAYAR ANGSURAN PPh PASAL 25 OPPT TAHUN PAJAK BERIUKUTNYA ?
I44: Tidak, saya tidak memliki kewajiban untuk membayar angsuran PPh Pasal 25.
I45: Ya, angsuran PPh Pasal 25 saya adalah 0,75 % dari penghasilan bruto setiap bulan dari masing-masing tempat usaha.
D47: I. | E47: PERNYATAAN TRANSAKSI LAINNYA
E49: 14 | F49: a | G49: HARTA PADA AKHIR TAHUN PAJAK (Isi Lampiran 1 Bagian A) | AL49: ='L1-2'!P60 -> 0
F51: b | G51: APAKAH ANDA MEMILIKI UTANG PADA AKHIR TAHUN PAJAK ? | AL51: ='L1-2'!AD82 -> 0
I52: Tidak. (Lanjut ke pertanyaan selanjutnya).
I53: Ya. (Isi Lampiran 1 Bagian B, lalu ke pertanyaan selanjutnya)
F55: c | G55: APAKAH ANDA MENERIMA PENGHASILAN YANG DIKENAKAN PAJAK PENGHASILAN BERSIFAT FINAL ?
I56: Tidak. (Lanjut ke pertanyaan selanjutnya).
I57: Ya. (Isi Lampiran 2 Bagian A, lalu ke pertanyaan selanjutnya)
F59: d | G59: APAKAH ANDA MENERIMA PENGHASILAN YANG TIDAK TERMASUK OBJEK PAJAK ? | AL59: ='L2'!AL57 -> 0
I60: Tidak. (Lanjut ke pertanyaan selanjutnya).
I61: Ya. (Isi Lampiran 2 Bagian B, lalu ke pertanyaan selanjutnya)
F63: e | G63: APAKAH ANDA MELAPORKAN BIAYA PENYUSUTAN DAN/ATAU AMORTISASI FISKAL ?
I64: Tidak. (Lanjut ke pertanyaan selanjutnya).
I65: Ya. (Isi Lampiran 3 C, lalu ke pertanyaan selanjutnya)
F67: f | G67: APAKAH ANDA MELAPORKAN BIAYA ENTERTAINMENT, BIAYA PROMOSI, PENGGANTIAN ATAU IMBALAN DALAM BENTUK NATURA DAN/ATAU KENIKMATAN, SERTA PIUTANG YANG NYATA-NYATA TIDAK DAPAT DITAGIH ?
I69: Tidak. (Lanjut ke pertanyaan selanjutnya).
I70: Ya. (Isi Lampiran 3 D, lalu ke pertanyaan selanjutnya)
F72: g | G72: APAKAH ANDA MENERIMA DIVIDEN DAN/ATAU PENGHASILAN LAIN DARI LUAR NEGERI DAN MELAPORKANNYA SEBAGAI PENGHASILAN TIDAK TERMASUK OBJEK PAJAK ?
I74: Tidak. (Lanjut ke pertanyaan selanjutnya).
I75: Ya. (Pastikan Anda sudah menyampaikan laporan realisasi investasi secara terpisah)
F77: h | G77: KELEBIHAN PPh FINAL ATAS PENGHASILAN DARI USAHA DENGAN PEREDARAN BRUTO TERTENTU YANG DAPAT DIMINTAKAN PENGEMBALIAN | AL77: =L3B!BJ42 -> 0
G78: (Silahkan mengajukan permohonan pengembalian pajak yang seharusnya tidak terhutang secara terpisah)
D80: J. | E80: LAMPIRAN TAMBAHAN
E82: a | F82: LAPORAN KEUANGAN/LAPORAN KEUANGAN YANG TELAH DI AUDIT | AE82: TIDAK | AI82: YA
E84: b | F84: BUKTI PEMBAYARAN ZAKAT/SUMBANGAN KEAGAMAAN WAJIB | AE84: TIDAK | AI84: YA
E86: c | F86: BUKTI PEMOTONGAN/PEMUNGUTAN SEHUBUNGAN DENGAN KREDIT PAJAK LUAR NEGERI | AE86: TIDAK | AI86: YA
E88: d | F88: SURAT KUASA KHUSUS | AE88: TIDAK | AI88: YA
E90: e | F90: DOKUMEN LAINNYA | AE90: TIDAK | AI90: YA
D92: K. | E92: PERNYATAAN
G94: DENGAN MENYADARI SEPENUHNYA AKAN SEGALA AKIBATNYA TERMASUK SANKSI-SANKSI SESUAI DENGAN KETENTUAN PERUNDANG-UNDANGAN YANG BERLAKU, SAYA MENYATAKAN BAHWA APA YANG TELAH SAYA BERITAHUKAN DI ATAS BESERTA LAMPIRAN-LAMPIRANNYA ADALAH BENAR, LENGKAP, DAN JELAS.
E98: PENANDA TANGAN | L98: WAJIB PAJAK | R98: WAKIL /KUASA | AH98: TANGGAL | AK98: BULAN | AN98: TAHUN
E100: NIK/NPWP | K100: ='1'!J21 | L100: ='1'!K21 | M100: ='1'!L21 | N100: ='1'!M21 | O100: ='1'!N21 | P100: ='1'!O21 | Q100: ='1'!P21 | R100: ='1'!Q21 | ... Z100: ='1'!Y21
E102: NAMA LENGKAP | K102: ='1'!J23 | AH102: TANDA TANGAN

Sheet L1-1
D4: PERHATIAN: | N4: A. | O4: HARTA PADA AKHIR TAHUN PAJAK | AM4: LAMPIRAN 1
D5: LAMPIRAN INI DIISI OLEH WAJIB PAJAK UNTUK MELAPORKAN HARTA, UTANG, DAFTAR ANGGOTA KELUARGA YANG MENJADI TANGGUNGAN, PENGHASILAN NETO DALAM NEGERI DARI PEKERJAAN DAN/ATAU BUKTI PEMOTONGAN PEMUNGUTAN PPh | N5: B. | O5: UTANG PADA AKHIR TAHUN PAJAK
N6: C. | O6: DAFTAR ANGGOTA KELUARGA YANG MENJADI TANGGUNGAN | AM6: HALAMAN 1
N7: D. | O7: PENGHASILAN NETO DALAM NEGERI DAN PEKERJAAN
N8: E. | O8: DAFTAR BUKTI PEMOTONGAN/PEMUNGUTAN PPh
N9: NIK/NPWP | Q9: ='1'!J21 | R9: ='1'!K21 | S9: ='1'!L21 | T9: ='1'!M21 | U9: ='1'!N21 | V9: ='1'!O21 | W9: ='1'!P21 | X9: ='1'!Q21 | ... AF9: ='1'!Y21 | AM9: TAHUN PAJAK | AQ9: ='1'!E14 | AR9: ='1'!G14 | AS9: ='1'!I14 | AT9: ='1'!K14
C12: A. | D12: HARTA PADA AKHIR TAHUN PAJAK
C14: 1. | D14: KAS DAN SETARA KAS
C16: KODE | F16: DESKRIPSI | K16: NOMOR AKUN | O16: ATAS NAMA | T16: NAMA BANK/INSTITUSI | Z16: LOKASI HARTA | AE16: TAHUN PEROLEHAN | AI16: SALDO | AN16: KETERANGAN
AN17: (Harta PPS/Harta Investasi PPS) | AW17: - | AX17: -
C18: (1) | F18: (2) | K18: (3) | O18: (4) | T18: (5) | Z18: (6) | AE18: (7) | AI18: (8) | AN18: (9) | AW18: 0101 | AX18: UANG TUNAI/BANK NOTE/KOIN
C19: - | F19: =VLOOKUP(C19,$AW$17:$AX$26,2,FALSE()) -> - | AN19: - | AW19: 0102 | AX19: TABUNGAN (BANK/LEMBAGA KEUANGAN)
C20: - | F20: =VLOOKUP(C20,$AW$17:$AX$26,2,FALSE()) -> - | AW20: 0103 | AX20: GIRO
C21: - | F21: =VLOOKUP(C21,$AW$17:$AX$26,2,FALSE()) -> - | AW21: 0104 | AX21: DEPOSITO
C22: - | F22: =VLOOKUP(C22,$AW$17:$AX$26,2,FALSE()) -> - | AW22: 0105 | AX22: UANG ELEKTRONIK
C23: - | F23: =VLOOKUP(C23,$AW$17:$AX$26,2,FALSE()) -> - | AW23: 0106 | AX23: CEK
C24: - | F24: =VLOOKUP(C24,$AW$17:$AX$26,2,FALSE()) -> - | AW24: 0107 | AX24: WESSEL
C25: - | F25: =VLOOKUP(C25,$AW$17:$AX$26,2,FALSE()) -> - | AW25: 0108 | AX25: KERTAS KOMERSIAL
C26: JUMLAH TABEL 1 | AG26: 1 | AI26: =SUM(AI19:AI25) -> 0 | AW26: 0109 | AX26: SETARA KAS LAINNYA
C28: 2. | D28: PIUTANG
C30: KODE | F30: DESKRIPSI | K30: LOKASI PENERIMAPINJAMAN | O30: PENERIMA PINJAMAN | Z30: NILAI PIUTANG | AE30: TAHUN DIMULAI | AI30: SALDO PIUTANG SAAT INI | AN30: KETERANGAN
AN31: (Harta PPS/Harta Investasi PPS)
C33: (1) | F33: (2) | K33: (3) | O33: (4) | Z33: (5) | AE33: (6) | AI33: (7) | AN33: (8) | AW33: - | AX33: -
C34: - | F34: =VLOOKUP(C34,$AW$33:$AX$36,2,FALSE()) -> - | O34: NIK/NPWP | AW34: 0201 | AX34: PIUTANG USAHA
O35: NAMA | AW35: 0202 | AX35: PIUTANG AFILIASI
C36: - | F36: =VLOOKUP(C36,$AW$33:$AX$36,2,FALSE()) -> - | O36: NIK/NPWP | AW36: 0209 | AX36: PIUTANG LAINNYA
O37: NAMA
C38: - | F38: =VLOOKUP(C38,$AW$33:$AX$36,2,FALSE()) -> - | O38: NIK/NPWP
O39: NAMA
C40: - | F40: =VLOOKUP(C40,$AW$33:$AX$36,2,FALSE()) -> - | O40: NIK/NPWP
O41: NAMA
C42: - | F42: =VLOOKUP(C42,$AW$33:$AX$36,2,FALSE()) -> - | O42: NIK/NPWP
O43: NAMA
C44: JUMLAH TABEL 2 | AG44: 2 | AI44: =SUM(AI34:AM43) -> 0
C46: 3. | D46: INVESTASI/SEKURITAS
C48: KODE | F48: DESKRIPSI | K48: LOKASI HARTA | O48: BANK / INSTITUSI / PENERIMA INVESTASI | X48: NOMOR AKUN | AB48: HARGA PEROLEHAN | AG48: TAHUN PEROLEHAN | AK48: NILAI SAAT INI | AO48: KETERANGAN | AW48: - | AX48: -
AO49: =AN31 -> (Harta PPS/Harta Investasi PPS) | AW49: 0301 | AX49: SAHAM YANG DIBELI UNTUK DIJUAL KEMBALI
AW50: 0302 | AX50: SAHAM NON BURSA
C51: (1) | F51: (2) | K51: (3) | O51: (4) | X51: (5) | AB51: (6) | AG51: (7) | AK51: (8) | AO51: (9) | AW51: 0303 | AX51: SAHAM BURSA
C52: - | F52: =VLOOKUP(C52,$AW$48:$AX$60,2,FALSE()) -> - | O52: NPWP | AO52: - | AW52: 0304 | AX52: OBLIGASI PERUSAHAAN
O53: NAMA | AW53: 0305 | AX53: OBLIGASI PEMERINTAH
C54: - | F54: =VLOOKUP(C54,$AW$48:$AX$60,2,FALSE()) -> - | O54: NPWP | AO54: - | AW54: 0306 | AX54: SURAT UTANG LAINNYA
O55: NAMA | AW55: 0307 | AX55: KONTRAK INVESTASI KOLEKTIF (KIK) INDONESIA
C56: - | F56: =VLOOKUP(C56,$AW$48:$AX$60,2,FALSE()) -> - | O56: NPWP | AW56: 0308 | AX56: INSTRUMEN DERIVATIVE
O57: NAMA | AW57: 0309 | AX57: PENYERTAAN MODAL DALAM PERUSAHAAN LAIN YANG BUKAN ATAS SAHAM
C58: - | F58: =VLOOKUP(C58,$AW$48:$AX$60,2,FALSE()) -> - | O58: NPWP | AW58: 0310 | AX58: ASURANSI
O59: NAMA | AW59: 0311 | AX59: UNIT LINK DI ASURANSI
C60: - | F60: =VLOOKUP(C60,$AW$48:$AX$60,2,FALSE()) -> - | O60: NPWP | AW60: 0399 | AX60: INVESTASI LAINNYA
O61: NAMA
C62: JUMLAH TABEL 3 | Z62: 3.6 | AB62: =SUM(AB52:AF61) -> 0 | AI62: 3.8 | AK62: =SUM(AK52:AN61) -> 0
C64: 4. | D64: HARTA BERGERAK
C66: KODE | F66: DESKRIPSI | M66: NOMOR POLISI/REGISTRASI | Q66: KEPEMILIKAN | AB66: TAHUN PEROLEHAN | AF66: HARGA PEROLEHAN | AK66: NILAI SAAT INI | AO66: KETERANGAN
AO67: =AO49 -> (Harta PPS/Harta Investasi PPS)
C69: (1) | F69: (2) | M69: (3) | Q69: (4) | AB69: (5) | AF69: (6) | AK69: (7) | AO69: (8)
C70: - | AW70: - | AX70: -
F71: TIPE | H71: =VLOOKUP(C70,$AW$70:$AX$83,2,FALSE()) -> - | S71: ATAS NAMA SENDIRI | AW71: 0401 | AX71: SEPEDA
AW72: 0402 | AX72: SEPEDA MOTOR
F73: MEREK/MODEL | S73: ATAS NAMA PIHAK LAIN | AW73: 0403 | AX73: MOBIL PENUMPANG
R74: NIK/NPWP: | AW74: 0404 | AX74: BUS
R75: NAMA: | AW75: 0405 | AX75: KENDARAAN ANGKUTAN JALAN
C76: - | AW76: 0406 | AX76: KENDARAAN TUJUAN KHUSUS
F77: TIPE | H77: =VLOOKUP(C76,$AW$70:$AX$83,2,FALSE()) -> - | S77: ATAS NAMA SENDIRI | AW77: 0407 | AX77: KERETA
AW78: 0408 | AX78: PESAWAT TERBANG
F79: MEREK/MODEL | S79: ATAS NAMA PIHAK LAIN | AW79: 0409 | AX79: KAPAL
R80: NIK/NPWP: | AW80: 0410 | AX80: MESIN
R81: NAMA: | AW81: 0411 | AX81: GEROBAK
C82: - | AW82: 0412 | AX82: KAPAL PESIAR
F83: TIPE | H83: =VLOOKUP(C82,$AW$70:$AX$83,2,FALSE()) -> - | S83: ATAS NAMA SENDIRI | AW83: 0499 | AX83: HARTA BERGERAK LAINNYA
F85: MEREK/MODEL | S85: ATAS NAMA PIHAK LAIN
R86: NIK/NPWP:
R87: NAMA:
C88: -
F89: TIPE | H89: =VLOOKUP(C88,$AW$70:$AX$83,2,FALSE()) -> - | S89: ATAS NAMA SENDIRI
F91: MEREK/MODEL | S91: ATAS NAMA PIHAK LAIN
R92: NIK/NPWP:
R93: NAMA:
C94: -
F95: TIPE | H95: =VLOOKUP(C94,$AW$70:$AX$83,2,FALSE()) -> - | S95: ATAS NAMA SENDIRI
F97: MEREK/MODEL | S97: ATAS NAMA PIHAK LAIN
R98: NIK/NPWP:
R99: NAMA:
C100: JUMLAH TABEL 4 | AD100: 4 | AF100: =SUM(AF71:AJ99) -> 0 | AK100: =SUM(AK71:AN99) -> 0

Sheet L1-2
D4: PERHATIAN: | N4: A. | O4: HARTA PADA AKHIR TAHUN PAJAK | AM4: LAMPIRAN 1
D5: LAMPIRAN INI DIISI OLEH WAJIB PAJAK UNTUK MELAPORKAN HARTA, UTANG, DAFTAR ANGGOTA KELUARGA YANG MENJADI TANGGUNGAN, PENGHASILAN NETO DALAM NEGERI DARI PEKERJAAN DAN/ATAU BUKTI PEMOTONGAN PEMUNGUTAN PPh | N5: B. | O5: UTANG PADA AKHIR TAHUN PAJAK
N6: C. | O6: DAFTAR ANGGOTA KELUARGA YANG MENJADI TANGGUNGAN | AM6: HALAMAN 2
N7: D. | O7: PENGHASILAN NETO DALAM NEGERI DAN PEKERJAAN
N8: E. | O8: DAFTAR BUKTI PEMOTONGAN/PEMUNGUTAN PPh
N9: NIK/NPWP | Q9: ='1'!J21 | R9: ='1'!K21 | S9: ='1'!L21 | T9: ='1'!M21 | U9: ='1'!N21 | V9: ='1'!O21 | W9: ='1'!P21 | X9: ='1'!Q21 | ... AF9: ='1'!Y21 | AM9: TAHUN PAJAK | AQ9: ='1'!E14 | AR9: ='1'!G14 | AS9: ='1'!I14 | AT9: ='1'!K14
C12: A. | D12: HARTA PADA AKHIR TAHUN PAJAK
C14: 5. | D14: HARTA TIDAK BERGERAK
C16: KODE | E16: DESKRIPSI | I16: LOKASI HARTA | M16: UKURAN PROPERTI | R16: SUMBER KEPEMILIKAN | W16: NOMOR SERTIPIKAT | AB16: TAHUN PEROLEHAN | AF16: HARGA PEROLEHAN | AJ16: NILAI SAAT INI | AN16: KETERANGAN
AN17: (Harta PPS/Harta Investasi PPS)
C18: (1) | E18: (2) | I18: (3) | M18: (4) | R18: (5) | W18: (6) | AB18: (7) | AF18: (8) | AJ18: (9) | AN18: (10) | AW18: - | AX18: -
C19: - | E19: =VLOOKUP(C19,$AW$18:$AX$26,2,FALSE()) -> - | M19: TANAH: | AW19: 0501 | AX19: TANAH KOSONG
M20: BANGUNAN: | AW20: 0502 | AX20: TANAH DAN/ATAU BANGUNAN UNTUK TEMPAT TINGGAL
C21: - | E21: =VLOOKUP(C21,$AW$18:$AX$26,2,FALSE()) -> - | M21: TANAH: | AW21: 0503 | AX21: APARTEMEN
M22: BANGUNAN: | AW22: 0504 | AX22: VESSEL
C23: - | E23: =VLOOKUP(C23,$AW$18:$AX$26,2,FALSE()) -> - | M23: TANAH: | AW23: 0505 | AX23: TANAH ATAU LAHAN UNTUK USAHA (LAHAN PERTANIAN, PERKEBUNAN, DSB)
M24: BANGUNAN: | AW24: 0506 | AX24: TANAH DAN/ATAU BANGUNAN UNTUK USAHA (TOKO, PABRIK, DSB)
C25: - | E25: =VLOOKUP(C25,$AW$18:$AX$26,2,FALSE()) -> - | M25: TANAH: | AW25: 0507 | AX25: TANAH DAN/ATAU BANGUNAN YANG DISEWAKAN
M26: BANGUNAN: | AW26: 0509 | AX26: HARTA TIDAK BERGERAK LAINNYA
C27: - | E27: =VLOOKUP(C27,$AW$18:$AX$26,2,FALSE()) -> - | M27: TANAH:
M28: BANGUNAN:
C29: - | E29: =VLOOKUP(C29,$AW$18:$AX$26,2,FALSE()) -> - | M29: TANAH:
M30: BANGUNAN:
C31: JUMLAH TABEL 5 | AD31: 5 | AF31: =SUM(AF19:AF29) -> 0 | AJ31: =SUM(AJ19:AJ29) -> 0
C33: 6. | D33: HARTA LAINNYA
C35: KODE | E35: DESKRIPSI | O35: TAHUN PEROLEHAN | S35: BUKTI KEPEMILIKAN/NOMOR AKUN | Z35: INFORMASI TAMBAHAN | AF35: HARGA PEROLEHAN | AJ35: NILAI SAAT INI | AN35: KETERANGAN
AN36: (Harta PPS/Harta Investasi PPS)
C38: (1) | E38: (2) | O38: (3) | S38: (4) | Z38: (5) | AF38: (6) | AJ38: (7) | AN38: (8) | AW38: - | AX38: -
C39: - | E39: =VLOOKUP(C39,$AW$38:$AX$55,2,FALSE()) -> - | AW39: 0601 | AX39: PATEN
C40: - | E40: =VLOOKUP(C40,$AW$38:$AX$55,2,FALSE()) -> - | AW40: 0602 | AX40: ROYALTI
C41: - | E41: =VLOOKUP(C41,$AW$38:$AX$55,2,FALSE()) -> - | AW41: 0603 | AX41: MEREK DAGANG
C42: - | E42: =VLOOKUP(C42,$AW$38:$AX$55,2,FALSE()) -> - | AW42: 0699 | AX42: HARTA TIDAK BERWUJUD LAINNYA
C43: - | E43: =VLOOKUP(C43,$AW$38:$AX$55,2,FALSE()) -> - | AW43: 0701 | AX43: EMAS BATANGAN
C44: - | E44: =VLOOKUP(C44,$AW$38:$AX$55,2,FALSE()) -> - | AW44: 0702 | AX44: EMAS PERHIASAN
C45: - | E45: =VLOOKUP(C45,$AW$38:$AX$55,2,FALSE()) -> - | AW45: 0703 | AX45: BATANGAN NON EMAS
C46: - | E46: =VLOOKUP(C46,$AW$38:$AX$55,2,FALSE()) -> - | AW46: 0704 | AX46: PERHIASAN NON EMAS
C47: - | E47: =VLOOKUP(C47,$AW$38:$AX$55,2,FALSE()) -> - | AW47: 0705 | AX47: PERMATA
C48: - | E48: =VLOOKUP(C48,$AW$38:$AX$55,2,FALSE()) -> - | AW48: 0706 | AX48: BARANG-BARANG SENI DAN ANTIK
C49: - | E49: =VLOOKUP(C49,$AW$38:$AX$55,2,FALSE()) -> - | AW49: 0707 | AX49: PERALATAN OLAH RAGA KHUSUS
C50: - | E50: =VLOOKUP(C50,$AW$38:$AX$55,2,FALSE()) -> - | AW50: 0708 | AX50: PERALATAN ELEKTRONIK
... C53: - | E53: =VLOOKUP(C53,$AW$38:$AX$55,2,FALSE()) -> - | AW53: 0711 | AX53: JET SKI
C54: JUMLAH TABEL 6 | AD54: 6 | AF54: =SUM(AF39:AF53) -> 0 | AJ54: =SUM(AJ39:AJ53) -> 0 | AW54: 0712 | AX54: PERSEDIAAN USAHA
AW55: 0799 | AX55: HARTA LAINNYA
C56: 7. | D56: IKHTISAR HARTA
C58: DESKRIPSI | P58: HARGA PEROLEHAN | Z58: NILAI SAAT INI
C59: (1) | P59: (2) | Z59: (3)
C60: JUMLAH HARTA PADA AKHIR TAHUN | N60: 7 | P60: ='L1-1'!AI26+'L1-1'!AI44+'L1-1'!AB62+'L1-1'!AF100+AF31+AF54 -> 0 | Z60: ='L1-1'!AK62+'L1-1'!AK100+AJ31+AJ54 -> 0
P61: JUMLAHKAN HARTA PADA TABEL 1 SAMPAI DENGAN TABEL 6 DI TABEL 7 KOLOM (2)
P62: PINDAHKAN JUMLAH HARTA TABEL 7 KOLOM (2) KE INDUK BAGIAN I ANGKA 14 HURUF a.
C64: B. | D64: UTANG PADA AKHIR TAHUN PAJAK
C66: KODE | E66: DESKRIPSI | L66: KREDITUR | T66: NEGARA KREDITUR | Z66: TAHUN PEMINJAMAN | AD66: SALDO | AN66: KETERANGAN
C69: (1) | E69: (2) | L69: (3) | T69: (4) | Z69: (5) | AD69: (6) | AN69: (7) | AW69: - | AX69: -
C70: - | E70: =VLOOKUP(C70,$AW$69:$AX$73,2,FALSE()) -> - | L70: NIK/NPWP: | AW70: 101 | AX70: UTANG BANK/LEMBAGA KEUANGAN BUKAN BANK
L71: NAMA: | AW71: 102 | AX71: KARTU KREDIT
C72: - | E72: =VLOOKUP(C72,$AW$69:$AX$73,2,FALSE()) -> - | L72: NIK/NPWP: | AW72: 103 | AX72: UTANG AFILIASI
L73: NAMA: | AW73: 109 | AX73: UTANG LAINNYA
C74: - | E74: =VLOOKUP(C74,$AW$69:$AX$73,2,FALSE()) -> - | L74: NIK/NPWP:
L75: NAMA:
C76: - | E76: =VLOOKUP(C76,$AW$69:$AX$73,2,FALSE()) -> - | L76: NIK/NPWP:
L77: NAMA:
C78: - | E78: =VLOOKUP(C78,$AW$69:$AX$73,2,FALSE()) -> - | L78: NIK/NPWP:
L79: NAMA:
C80: - | E80: =VLOOKUP(C80,$AW$69:$AX$73,2,FALSE()) -> - | L80: NIK/NPWP:
L81: NAMA:
C82: JUMLAH TABEL B | AB82: B | AD82: =SUM(AD70:AM81) -> 0
C83: PINDAHKAN JUMLAH TABEL B KE INDUK BAGIAN I ANGKA 14 HURUF b.
AR85: HOME

Sheet L1-3
D4: PERHATIAN: | N4: A. | O4: HARTA PADA AKHIR TAHUN PAJAK | AM4: LAMPIRAN 1
D5: LAMPIRAN INI DIISI OLEH WAJIB PAJAK UNTUK MELAPORKAN HARTA, UTANG, DAFTAR ANGGOTA KELUARGA YANG MENJADI TANGGUNGAN, PENGHASILAN NETO DALAM NEGERI DARI PEKERJAAN DAN/ATAU BUKTI PEMOTONGAN PEMUNGUTAN PPh | N5: B. | O5: UTANG PADA AKHIR TAHUN PAJAK
N6: C. | O6: DAFTAR ANGGOTA KELUARGA YANG MENJADI TANGGUNGAN | AM6: HALAMAN 3
N7: D. | O7: PENGHASILAN NETO DALAM NEGERI DAN PEKERJAAN
N8: E. | O8: DAFTAR BUKTI PEMOTONGAN/PEMUNGUTAN PPh
N9: NIK/NPWP | Q9: ='1'!J21 | R9: ='1'!K21 | S9: ='1'!L21 | T9: ='1'!M21 | U9: ='1'!N21 | V9: ='1'!O21 | W9: ='1'!P21 | X9: ='1'!Q21 | ... AF9: ='1'!Y21 | AM9: TAHUN PAJAK | AQ9: ='1'!E14 | AR9: ='1'!G14 | AS9: ='1'!I14 | AT9: ='1'!K14
C12: C. | D12: DAFTAR ANGGOTA KELUARGA YANG MENJADI TANGGUNGAN
AW13: -
C14: NAMA | M14: NIK | T14: TANGGAL LAHIR | AA14: HUBUNGAN DENGAN WAJIB PAJAK | AJ14: PEKERJAAN | AW14: Mengurus Rumah Tangga
AW15: Pelajar/Mahasiswa
C16: (1) | M16: (2) | T16: (3) | AA16: (4) | AJ16: (5) | AW16: Pensiunan
AA17: - | AW17: Anggota TNI/POLRI
AA18: - | AW18: Karyawan Swasta
AW19: Petani/Pekebun
AW20: Buruh Harian Lepas
AW21: Dokter
AA22: - | AJ22: - | AW22: Wirawasta
AA23: - | AJ23: - | AW23: Tidak Bekerja
C25: D. | D25: PENGHASILAN NETO DALAM NEGERI DARI PEKERJAAN
B27: HOME | C27: NO. | D27: NAMA PEMBERI KERJA | L27: NOMOR IDENTITAS PEMBERI KERJA | T27: PENGHASILAN BRUTO | AA27: PENGURANG PENGHASILAN BRUTO | AJ27: PENGHASILAN NETO
C29: (1) | D29: (2) | L29: (3) | T29: (4) | AA29: (5) | AJ29: (6)
AJ30: =T30-AA30 -> 0
C36: JUMLAH TABEL D | AH36: D | AJ36: =SUM(AJ30:AJ35) -> 0
AF37: PINDAHKAN JUMLAH TABEL D KE INDUK BAGIAN B ANGKA 1 HURUF a.
C38: E. | D38: DAFTAR BUKTI PEMOTONGAN/PEMUNGUTAN PPh
C40: NO. | D40: PEMOTONG/PEMUNGUT PPh | N40: BUKTI PEMOTONGAN/PEMUNGUTAN | V40: JENIS PAJAK | AA40: PENGHASILAN BRUTO | AM40: JUMLAH PPh YANG DIPOTONG/DIPUNGUT
C42: (1) | D42: (2) | N42: (3) | V42: (4) | AA42: (5) | AM42: (6) | AW42: -
D43: NIK/NPWP: | N43: NOMOR: | V43: - | AW43: PPh Pasal 21
D44: NAMA: | N44: TANGGAL: | AW44: PPh Pasal 22
D45: NIK/NPWP: | N45: NOMOR: | V45: - | AW45: PPh Pasal 23
D46: NAMA: | N46: TANGGAL: | AW46: PPh Pasal 26
D47: NIK/NPWP: | N47: NOMOR: | V47: - | AW47: PPh ditanggung pemerintah (DTP)
D48: NAMA: | N48: TANGGAL:
D49: NIK/NPWP: | N49: NOMOR: | V49: - | AW49: -
D50: NAMA: | N50: TANGGAL: | AW50: Anak
D51: NIK/NPWP: | N51: NOMOR: | V51: - | AW51: Cucu
D52: NAMA: | N52: TANGGAL: | AW52: Kepala Keluarga
D53: NIK/NPWP: | N53: NOMOR: | V53: - | AW53: Suami
D54: NAMA: | N54: TANGGAL: | AW54: Mertua
D55: NIK/NPWP: | N55: NOMOR: | V55: - | AW55: Pembantu
D56: NAMA: | N56: TANGGAL: | AW56: Lainnya
D57: NIK/NPWP: | N57: NOMOR: | V57: - | AW57: Family Lain
D58: NAMA: | N58: TANGGAL: | AW58: Orang Tua
D59: NIK/NPWP: | N59: NOMOR: | V59: - | AW59: Menantu
D60: NAMA: | N60: TANGGAL: | AW60: Istri
D61: NIK/NPWP: | N61: NOMOR: | V61: - | AW61: Anak Tiri
D62: NAMA: | N62: TANGGAL: | AW62: Anak Angkat
D63: NIK/NPWP: | N63: NOMOR: | V63: - | AW63: Kakek
D64: NAMA: | N64: TANGGAL: | AW64: Nenek
D65: NIK/NPWP: | N65: NOMOR: | V65: - | AW65: Kakek dan Suami/Istri
D66: NAMA: | N66: TANGGAL: | AW66: Nenek dari Suami/Istri
D67: NIK/NPWP: | N67: NOMOR: | V67: -
D68: NAMA: | N68: TANGGAL:
D69: NIK/NPWP: | N69: NOMOR: | V69: -
D70: NAMA: | N70: TANGGAL:
C71: JUMLAH KREDIT PAJAK DALAM NEGERI | AK71: 16 | AM71: =SUM(AM43:AM69) -> 0
C72: KREDIT PAJAK ATAS PENGHASILAN DARI LUAR NEGERI (DIISI DARI LAMPIRAN 2 JUMLAH TABEL C.10) | AK72: 17 | AM72: ='L2'!AP73 -> 0
C73: JUMLAH TABEL E (16) + (17) | AK73: E | AM73: =AM71+AM72 -> 0
AF74: PINDAHKAN JUMLAH TABEL E KE INDUK BAGIAN D ANGKA 10 HURUF a.
AR75: HOME

Sheet L2
D4: PERHATIAN: | N4: A. | O4: PENGHASILAN YANG DIKENAKAN PAJAK PENGHASILAN BERSIFAT FINAL | AM4: LAMPIRAN 2
D5: LAMPIRAN INI DIISI OLEH WAJIB PAJAK UNTUK MELAPORKAN PENGHASILAN YANG DIKENAKAN PPh YANG BERSIFAT FINAL, PENGHASILAN YANG TIDAK TERMASUK OBJEK PAJAK DAN/ATAU PENGHASILAN NETO LUAR NEGERI | N5: B. | O5: PENGHASILAN YANG TIDAK TERMASUK OBJEK PAJAK
N6: C. | O6: PENGHASILAN NETO LUAR NEGERI
N8: NIK/NPWP | Q8: ='1'!J21 | R8: ='1'!K21 | S8: ='1'!L21 | T8: ='1'!M21 | U8: ='1'!N21 | V8: ='1'!O21 | W8: ='1'!P21 | X8: ='1'!Q21 | ... AF8: ='1'!Y21 | AM8: TAHUN PAJAK | AQ8: ='1'!E14 | AR8: ='1'!G14 | AS8: ='1'!I14 | AT8: ='1'!K14
C11: A. | D11: PENGHASILAN YANG DIKENAKAN PAJAK PENGHASILAN BERSIFAT FINAL
C13: NO. | D13: PEMOTONG/PEMUNGUT PPh | N13: KODE | Q13: JENIS PENGHASILAN | Z13: DASAR PENGENAAN PAJAK | AI13: PPh TERUTANG | AW13: - | AX13: -
AW14: 28-423-01 | AX14: pemotongan/Pemungutan PPh final bagi WP dengan peredaran bruto tertentu
C15: (1) | D15: (2) | N15: (3) | Q15: (4) | Z15: (5) | AI15: (6) | AW15: 28-423-99 | AX15: PPh final sesuai PP-55/2022 (Disetor Sendiri)
C16: 1 | D16: NIK/NPWP: | N16: - | Q16: =VLOOKUP(N16,$AW$13:$AX$26,2,FALSE()) -> - | AW16: 28-404-01 | AX16: bunga tabungan dan bunga deposito yang ditempatkan di DN selain dari DHE)
D17: NAMA: | AW17: 28-401-01 | AX17: bunga obligasi, SUN, atau obligasi daerah yang diterima WP DN dan BUT
C18: 2 | D18: NIK/NPWP: | N18: - | Q18: =VLOOKUP(N18,$AW$13:$AX$26,2,FALSE()) -> - | AI18: =Z18*20% -> 0 | AW18: 28-406-01 | AX18: transaksi penjualan saham di bursa efek (bukan saham pendiri)
D19: NAMA: | AW19: 21-401-01 | AX19: uang pesangon yang dibayarkan sekaligus
C20: 3 | D20: NIK/NPWP: | N20: - | Q20: =VLOOKUP(N20,$AW$13:$AX$26,2,FALSE()) -> - | AI20: =Z20*10% -> 0 | AW20: 21-402-02 | AX20: honor atau imbalan lain APBN atau APBD yang diterima PNS/TNI/POLRI dan pensiunannya
D21: NAMA: | AW21: 28-405-01 | AX21: Hadiah Undian
C22: 4 | D22: NIK/NPWP: | N22: - | Q22: =VLOOKUP(N22,$AW$13:$AX$26,2,FALSE()) -> - | AI22: =Z22*10% -> 0 | AW22: 28-417-02 | AX22: bunga simpanan yang dibayarkan oleh koperasi kepada anggota WP OP
D23: NAMA: | AW23: 28-419-01 | AX23: dividen yang diterima/diperoleh WP OP DN
D24: NIK/NPWP: | N24: - | Q24: =VLOOKUP(N24,$AW$13:$AX$26,2,FALSE()) -> - | AW24: 28-402-01 | AX24: pengalihan hak atas tanah dan/atau bangunan
D25: NAMA: | AW25: 28-403-02 | AX25: persewaan tanah dan/atau bangunan
D26: NIK/NPWP: | N26: - | Q26: =VLOOKUP(N26,$AW$13:$AX$26,2,FALSE()) -> - | AW26: 28-409-10 | AX26: jasa konstruksi berupa jasa pelaksanaan konstruksi (kualifikasi usaha kecil)
D27: NAMA: | AW27: 28-499-99 | AX27: penghasilan istri dari satu pemberi kerja yang hak dan kewajiban perpajakannya dilaksanakan oleh kepala keluarga
D28: NIK/NPWP: | N28: - | Q28: =VLOOKUP(N28,$AW$13:$AX$26,2,FALSE()) -> -
D29: NAMA:
D30: NIK/NPWP: | N30: - | Q30: =VLOOKUP(N30,$AW$13:$AX$26,2,FALSE()) -> -
D31: NAMA:
D32: NIK/NPWP: | N32: - | Q32: =VLOOKUP(N32,$AW$13:$AX$26,2,FALSE()) -> -
D33: NAMA:
D34: NIK/NPWP: | N34: - | Q34: =VLOOKUP(N34,$AW$13:$AX$26,2,FALSE()) -> -
D35: NAMA:
D36: NIK/NPWP: | N36: - | Q36: =VLOOKUP(N36,$AW$13:$AX$26,2,FALSE()) -> -
D37: NAMA:
D38: NIK/NPWP: | N38: - | Q38: =VLOOKUP(N38,$AW$13:$AX$26,2,FALSE()) -> -
D39: NAMA:
D40: NIK/NPWP: | N40: - | Q40: =VLOOKUP(N40,$AW$13:$AX$26,2,FALSE()) -> -
D41: NAMA: | AV41: HOME
C42: JUMLAH TABEL A | X42: A | Z42: =SUM(Z16:Z40) -> 0 | AI42: =SUM(AI16:AI40) -> 0
AD43: PINDAHKAN JUMLAH TABEL A KOLOM (5) KE INDUK BAGIAN I ANGKA 14 HURUF c.
C45: B. | D45: PENGHASILAN YANG TIDAK TERMASUK OBJEK PAJAK
AY46: - | AZ46: -
C47: NO. | D47: KODE | M47: JENIS PENGHASILAN | V47: SUMBER PENGHASILAN | AL47: PENGHASILAN BRUTO | AY47: 303 | AZ47: Dividen atau bagian laba
V48: NIK/NPWP | AD48: NAMA | AY48: 401 | AZ48: Pembebasan utang
C49: (1) | D49: (2) | M49: (3) | V49: (4) | AD49: (5) | AL49: (6) | AY49: 402 | AZ49: Hibah
C50: 1 | D50: - | M50: =VLOOKUP(D50,$AY$46:$AZ$60,2,FALSE()) -> - | AY50: 403 | AZ50: Bantuan/sumbangan
C51: 2 | D51: - | M51: =VLOOKUP(D51,$AY$46:$AZ$60,2,FALSE()) -> - | AY51: 404 | AZ51: Warisan
C52: 3 | D52: - | M52: =VLOOKUP(D52,$AY$46:$AZ$60,2,FALSE()) -> - | AY52: 405 | AZ52: Penerimaan zakat
D53: - | M53: =VLOOKUP(D53,$AY$46:$AZ$60,2,FALSE()) -> - | AY53: 406 | AZ53: Bagian laba anggota CV
D54: - | M54: =VLOOKUP(D54,$AY$46:$AZ$60,2,FALSE()) -> - | AY54: 407 | AZ54: Klaim Asuransi
D55: - | M55: =VLOOKUP(D55,$AY$46:$AZ$60,2,FALSE()) -> - | AY55: 408 | AZ55: Beasiswa
D56: - | M56: =VLOOKUP(D56,$AY$46:$AZ$60,2,FALSE()) -> - | AV56: HOME | AY56: 409 | AZ56: Hadiah
C57: JUMLAH TABEL B | AJ57: B | AL57: =SUM(AL50:AL56) -> 0 | AY57: 423 | AZ57: Objek PPh tertentu bagi TKA tertentu
AF58: PINDAHKAN JUMLAH TABEL B KE INDUK BAGIAN I ANGKA 14 HURUF d. | AY58: 424 | AZ58: Natura dan Kenikmatan yang dikecualikan
AY59: 425 | AZ59: SHU Koperasi
C60: C. | D60: PENGHASILAN NETO LUAR NEGERI | AY60: 498 | AZ60: Penghasilan lain yang tidak termasuk objek pajak
C62: NO. | D62: SUMBER/ PEMBERI PENGHASILAN | M62: TANGGAL TRANSAKSI | P62: JENIS PENGHASILAN | T62: PENGHASILAN NETO | X62: PAJAK PENGHASILAN YANG TERUTANG/DIBAYAR/DIPOTONG DI LUAR NEGERI | AP62: KREDIT PAJAK YANG DAPAT DIPERHITUNGKAN
X63: NILAI DALAM MATA UANG ASING | AD63: NILAI DALAM RUPIAH | AJ63: MATA UANG ASING
D64: NAMA | I64: NEGARA
C65: (1) | D65: (2) | I65: (3) | M65: (4) | P65: (5) | T65: (6) | X65: (7) | AD65: (8) | AJ65: (9) | AP65: (10)
P66: -
P67: -
P68: -
P69: -
P70: -
P71: -
P72: -
C73: JUMLAH TABEL C | R73: C.6 | T73: =SUM(T66:T72) -> 0 | AB73: C.8 | AD73: =SUM(AD66:AD72) -> 0 | AN73: C.10 | AP73: =SUM(AP66:AP72) -> 0 | AV73: HOME
D74: PINDAHKAN JUMLAH TABEL C KOLOM (6) KE INDUK BAGIAN B ANGKA 1 HURUF d. | Z74: PINDAHKAN JUMLAH TABEL C KOLOM (10) KE LAMPIRAN 1 BAGIAN E HURUF E BARIS 17 KOLOM (6)
P76: - | Q76: -
P77: 104 | Q77: Penghasilan dari pekerjaan bebas
P78: 109 | Q78: Penghasilan dari kegiatan usaha
P79: 199 | Q79: Pendapatan lain dari kegiatan usaha atau pekerjaan bebas
P80: 201 | Q80: Gaji, tunjangan, honorarium, bonus, jasa produksi
P81: 202 | Q81: Upah dan honorarium yang diterima oleh pegawai tidak tetap
P82: 204 | Q82: Uang pesangon diterima sekaligus
P83: 205 | Q83: Manfaat Pensiun, Tunjangan Hari Tua, atau Jaminan Hari Tua dibayarkan sekaligus
P84: 206 | Q84: Uang Pensiun yang diterima secara berkala/bulanan oleh penerima pensiun
P85: 299 | Q85: Penghasilan lain yang berhubungan dengan pekerjaan
P86: 301 | Q86: Sewa tanah dan/atau bangunan
P87: 302 | Q87: Sewa harta selain tanah dan/atau bangunan
P88: 303 | Q88: Dividen
... P104: 499 | Q104: Penghasilan lain

Sheet L3A-1
B4: HOME | D4: PERHATIAN: | O4: REKONSILIASI LAPORAN KEUANGAN (DAGANG) | AH4: LAMPIRAN 3A-1
D5: LAMPIRAN INI HARUS DIISI OLEH WAJIB PAJAK YANG MENYELENGGARAKAN PEMBUKUAN STELSEL KAS ATAU PEMBUKUAN STELSEL AKRUAL DI SEKTOR USAHA DAGANG
N8: NIK/NPWP | AH8: TAHUN PAJAK | AL8: ='1'!E14 | AM8: ='1'!G14 | AN8: ='1'!I14 | AO8: ='1'!K14
C11: A.1 | D11: LAPORAN LABA RUGI
C13: KODE AKUN | E13: NAMA AKUN | K13: NILAI KOMERSIAL | O13: TIDAK TERMASUK OBJEK PAJAK | S13: DIKENAKAN PPh FINAL | W13: OBJEK PAJAK TIDAK FINAL | AA13: PENYESUAIAN FISKAL POSITIF | AE13: PENYESUAIAN FISKAL NEGATIF | AI13: KODE PENYESUAIAN FISKAL | AM13: NILAI FISKAL
C16: (1) | E16: (2) | K16: (3) | O16: (4) | S16: (5) | W16: (6) | AA16: (7) | AE16: (8) | AI16: (9) | AM16: (10)
E17: PENJUALAN
C18: 4002 | E18: PENJUALAN DOMESTIK
C19: 4003 | E19: PENJUALAN EKSPOR
C20: 4004 | E20: PENJUALAN BRUTO
E21: DIKURANGI:
C22: 4011 | E22: RETUR
C23: 4012 | E23: POTONGAN PENJUALAN
C24: 4020 | E24: PENJUALAN BERSIH
E25: HARGA POKOK PENJUALAN:
C26: 5001 | E26: PEMBELIAN
C27: 5008 | E27: PERSEDIAAN AWAL
C28: 5009 | E28: DIKURANGI: PERSEDIAAN AKHIR
C29: 5020 | E29: JUMLAH HARGA POKOK PENJUALAN
C30: 4300 | E30: LABA KOTOR | AR30: FPO-01 | AS30: Biaya yang dibebankan/dikeluarkan untuk kepentingan pribadi Wajib Pajak atau orang yang menjadi tanggungannya
E31: BEBAN USAHA | AR31: FPO-02 | AS31: Premi Asuransi kesehatan, asuransi kecelakaan, asuransi jiwa, asuransi dwiguna, dan asuransi beasiswa yang dibayar oleh Wajib Pajak
C32: 5311 | E32: BEBAN GAJI, TUNJANGAN, BONUS, HONORARIUM, THR, DLL | AR32: FPO-04 | AS32: Jumlah yang melebihi kewajaran yang dibayarkan kepada pihak yang mempunyai hubungan istimewa sehubungan dengan pekerjaan yang dilakukan
C33: 5313 | E33: BEBAN TRANSPORTASI | AR33: FPO-05 | AS33: Harta yang dihibahkan, bantuan atau sumbangan
C34: 5314 | E34: BEBAN PENYUSUTAN DAN AMORTISASI | AR34: FPO-06 | AS34: Pajak penghasilan
C35: 5315 | E35: BEBAN SEWA | AR35: FPO-07 | AS35: Gaji yang dibayarkan kepada pemilik/orang yang menjadi tanggungannya
C36: 5316 | E36: BEBAN BUNGA | AR36: FPO-08 | AS36: Sanksi administrasi
C37: 5317 | E37: BEBAN SEHUBUNGAN DENGAN JASA | AR37: FPO-09 | AS37: Selisih penyusutan komersial di atas penyusutan fiskal
C38: 5318 | E38: BEBAN PIUTANG TIDAK TERTAGIH | AR38: FPO-10 | AS38: Selisih amortisasi komersial di atas amortisasi fiskal
C39: 5320 | E39: BEBAN PROMOSI/PEMASARAN | AR39: FPO-11 | AS39: Biaya untuk mendapatkan, menagih dan memelihara penghasilan yang dikenakan PPh Final dan penghasilan yang tidak termasuk objek pajak
C40: 5321 | E40: BEBAN ENTERTAINMENT | AR40: FPO-12 | AS40: Penyesuaian fiskal positif lainnya
C41: 5322 | E41: BEBAN UMUM DAN ADMINISTRASI | AR41: FNE-01 | AS41: Penghasilan yang dikenakan PPh final dan penghasilan yang tidak termasuk objek pajak tetapi termasuk dalam peredaran usaha
C42: 5399 | E42: BEBAN USAHA LAINNYA | AR42: FNE-02 | AS42: Selisih penyusutan komersial di bawah penyusutan fiska
C43: 5400 | E43: JUMLAH BEBAN USAHA | AR43: FNE-03 | AS43: Selisih amortisasi komersial di bawah amortisasi fiskal
C44: 4800 | E44: LABA (RUGI) SEBELUM PAJAK | AR44: FNE-04 | AS44: Penyesuaian fiskal negatif lainnya
X45: PINDAHKAN LABA (RUGI) SEBELUM PAJAK KOLOM (10) KE INDUK BAGIAN B ANGKA 1 HURUF b
C46: A.2 | D46: LAPORAN POSISI KEUANGAN (NERACA)
C48: KODE AKUN | E48: AKUN | W48: KODE AKUN | Y48: AKUN
C50: (1) | E50: (2) | W50: (1) | Y50: (2)
E51: ASET LANCAR | Y51: LIABILITAS JANGKA PENDEK | AR51: HOME
C52: 1101 | E52: KAS DAN SETARA KAS | W52: 2102 | Y52: UTANG USAHA - PIHAK KETIGA
C53: 1200 | E53: INVESTASI | W53: 2103 | Y53: UTANG USAHA - PIHAK YANG MEMPUNYAI HUBUNGAN ISTIMEWA
C54: 1122 | E54: PIUTANG USAHA - PIHAK KETIGA | W54: 2111 | Y54: UTANG BANK
C55: 1123 | E55: PIUTANG USAHA - PIHAK YANG MEMPUNYAI HUBUNGAN ISTIMEWA | W55: 2191 | Y55: UTANG PAJAK
C56: 1124 | E56: PIUTANG LAINNYA - PIHAK KETIGA | W56: 2192 | Y56: UTANG DIVIDEN
C57: 1125 | E57: PIUTANG LAINNYA - PIHAK YANG MEMPUNYAI HUBUNGAN ISTIMEWA | W57: 2196 | Y57: BEBAN YANG MASIH HARUS DIBAYAR
C58: 1131 | E58: DIKURANGI: CADANGAN PIUTANG TAK TERTAGIH | W58: 2201 | Y58: UTANG BANK JANGKA PENDEK
C59: 1401 | E59: PERSEDIAAN | W59: 2202 | Y59: UTANG JANGKA PANJANG YANG JATUH TEMPO DALAM SATU TAHUN
C60: 1421 | E60: BEBAN DIBAYAR DI MUKA | W60: 2203 | Y60: UANG MUKA
C61: 1422 | E61: UANG MUKA | W61: 2228 | Y61: LIABILITAS JANGKA PENDEK LAINNYA
C62: 1423 | E62: PAJAK DIBAYAR DI MUKA | Y62: LIABILITAS JANGKA PANJANG
C63: 1499 | E63: ASET LANCAR LAINNYA | W63: 2301 | Y63: UTANG BANK JANGKA PANJANG
E64: ASET TIDAK LANCAR | W64: 2303 | Y64: UTANG JANGKA PANJANG - PIHAK KETIGA
C65: 1501 | E65: PIUTANG JANGKA PANJANG | W65: 2304 | Y65: UTANG JANGKA PANJANG - PIHAK YANG MEMPUNYAI HUBUNGAN ISTIMEWA
C66: 1523 | E66: TANAH DAN BANGUNAN | W66: 2321 | Y66: LIABILITAS PAJAK TANGGUHAN
C67: 1524 | E67: DIKURANGI: AKUMULASI PENYUSUTAN | W67: 2998 | Y67: LIABILITAS JANGKA PANJANG LAINNYA
C68: 1529 | E68: ASET TETAP LAINNYA | W68: 2999 | Y68: JUMLAH LIABILITAS
C69: 1530 | E69: DIKURANGI: AKUMULASI PENYUSUTAN | Y69: EKUITAS
C70: 1541 | E70: INVESTASI PADA PERUSAHAAN ASOSIASI | W70: 3102 | Y70: MODAL SAHAM
C71: 1599 | E71: INVESTASI JANGKA PANJANG LAINNYA | W71: 3120 | Y71: TAMBAHAN MODAL DISETOR
C72: 1600 | E72: ASET TAK BERWUJUD - NET | W72: 3200 | Y72: SALDO LABA
C73: 1611 | E73: ASET PAJAK TANGGUHAN | W73: 3298 | Y73: EKUITAS LAINNYA
C74: 1698 | E74: ASET TIDAK LANCAR LAINNYA | W74: 3200 | Y74: JUMLAH EKUITAS
C75: 1700 | E75: JUMLAH ASET | W75: 3300 | Y75: JUMLAH LIABILITAS DAN EKUITAS
D78: LAPORAN KEUANGAN | K78: DIAUDIT | O78: TIDAK DIAUDIT
D82: NPWP KANTOR AKUNTAN PUBLIK | X82: NPWP KONSULTAN PUBLIK
D85: NAMA KANTOR AKUNTAN PUBLIK | X85: NAMA KONSULTAN PUBLIK
AO89: HOME

Sheet L3A-2
B4: HOME | D4: PERHATIAN: | O4: REKONSILIASI LAPORAN KEUANGAN (JASA) | AH4: LAMPIRAN 3A-2
D5: LAMPIRAN INI HARUS DIISI OLEH WAJIB PAJAK YANG MENYELENGGARAKAN PEMBUKUAN STELSEL KAS ATAU PEMBUKUAN STELSEL AKRUAL DI SEKTOR USAHA JASA
N8: NIK/NPWP | AH8: TAHUN PAJAK | AL8: ='1'!E14 | AM8: ='1'!G14 | AN8: ='1'!I14 | AO8: ='1'!K14
C11: A.1 | D11: LAPORAN LABA RUGI
C13: KODE AKUN | E13: NAMA AKUN | K13: NILAI KOMERSIAL | O13: TIDAK TERMASUK OBJEK PAJAK | S13: DIKENAKAN PPh FINAL | W13: OBJEK PAJAK TIDAK FINAL | AA13: PENYESUAIAN FISKAL POSITIF | AE13: PENYESUAIAN FISKAL NEGATIF | AI13: KODE PENYESUAIAN FISKAL | AM13: NILAI FISKAL
C16: (1) | E16: (2) | K16: (3) | O16: (4) | S16: (5) | W16: (6) | AA16: (7) | AE16: (8) | AI16: (9) | AM16: (10)
E17: PENDAPATAN
C18: 4002 | E18: PENDAPATAN JASA
C19: 4003 | E19: BIAYA POKOK JASA
C20: 4004 | E20: LABA KOTOR | AR20: FPO-01 | AS20: Biaya yang dibebankan/dikeluarkan untuk kepentingan pribadi Wajib Pajak atau orang yang menjadi tanggungannya
E21: BEBAN USAHA | AR21: FPO-02 | AS21: Premi Asuransi kesehatan, asuransi kecelakaan, asuransi jiwa, asuransi dwiguna, dan asuransi beasiswa yang dibayar oleh Wajib Pajak
C22: 5311 | E22: BEBAN GAJI, TUNJANGAN, BONUS, HONORARIUM, THR, DLL | AR22: FPO-04 | AS22: Jumlah yang melebihi kewajaran yang dibayarkan kepada pihak yang mempunyai hubungan istimewa sehubungan dengan pekerjaan yang dilakukan
C23: 5313 | E23: BEBAN TRANSPORTASI | AR23: FPO-05 | AS23: Harta yang dihibahkan, bantuan atau sumbangan
C24: 5314 | E24: BEBAN PENYUSUTAN DAN AMORTISASI | AR24: FPO-06 | AS24: Pajak penghasilan
C25: 5315 | E25: BEBAN SEWA | AR25: FPO-07 | AS25: Gaji yang dibayarkan kepada pemilik/orang yang menjadi tanggungannya
C26: 5316 | E26: BEBAN BUNGA | AR26: FPO-08 | AS26: Sanksi administrasi
C27: 5317 | E27: BEBAN SEHUBUNGAN DENGAN JASA | AR27: FPO-09 | AS27: Selisih penyusutan komersial di atas penyusutan fiskal
C28: 5318 | E28: BEBAN PIUTANG TIDAK TERTAGIH | AR28: FPO-10 | AS28: Selisih amortisasi komersial di atas amortisasi fiskal
C29: 5320 | E29: BEBAN PROMOSI/PEMASARAN | AR29: FPO-11 | AS29: Biaya untuk mendapatkan, menagih dan memelihara penghasilan yang dikenakan PPh Final dan penghasilan yang tidak termasuk objek pajak
C30: 5321 | E30: BEBAN ENTERTAINMENT | AR30: FPO-12 | AS30: Penyesuaian fiskal positif lainnya
C31: 5322 | E31: BEBAN UMUM DAN ADMINISTRASI | AR31: FNE-01 | AS31: Penghasilan yang dikenakan PPh final dan penghasilan yang tidak termasuk objek pajak tetapi termasuk dalam peredaran usaha
C32: 5399 | E32: BEBAN USAHA LAINNYA | AR32: FNE-02 | AS32: Selisih penyusutan komersial di bawah penyusutan fiska
C33: 5400 | E33: JUMLAH BEBAN USAHA | AR33: FNE-03 | AS33: Selisih amortisasi komersial di bawah amortisasi fiskal
C34: 4800 | E34: LABA (RUGI) SEBELUM PAJAK | AR34: FNE-04 | AS34: Penyesuaian fiskal negatif lainnya
X35: PINDAHKAN LABA (RUGI) SEBELUM PAJAK KOLOM (10) KE INDUK BAGIAN B ANGKA 1 HURUF b
C36: A.2 | D36: LAPORAN POSISI KEUANGAN (NERACA)
C38: KODE AKUN | E38: AKUN | W38: KODE AKUN | Y38: AKUN
C40: (1) | E40: (2) | W40: (1) | Y40: (2)
E41: ASET LANCAR | Y41: LIABILITAS JANGKA PENDEK
C42: 1101 | E42: KAS DAN SETARA KAS | W42: 2102 | Y42: UTANG USAHA - PIHAK KETIGA | AR42: HOME
C43: 1200 | E43: INVESTASI | W43: 2103 | Y43: UTANG USAHA - PIHAK YANG MEMPUNYAI HUBUNGAN ISTIMEWA
C44: 1122 | E44: PIUTANG USAHA - PIHAK KETIGA | W44: 2111 | Y44: UTANG BANK
C45: 1123 | E45: PIUTANG USAHA - PIHAK YANG MEMPUNYAI HUBUNGAN ISTIMEWA | W45: 2191 | Y45: UTANG PAJAK
C46: 1124 | E46: PIUTANG LAINNYA - PIHAK KETIGA | W46: 2192 | Y46: UTANG DIVIDEN
C47: 1125 | E47: PIUTANG LAINNYA - PIHAK YANG MEMPUNYAI HUBUNGAN ISTIMEWA | W47: 2196 | Y47: BEBAN YANG MASIH HARUS DIBAYAR
C48: 1131 | E48: DIKURANGI: CADANGAN PIUTANG TAK TERTAGIH | W48: 2201 | Y48: UTANG BANK JANGKA PENDEK
C49: 1401 | E49: PERSEDIAAN | W49: 2202 | Y49: UTANG JANGKA PANJANG YANG JATUH TEMPO DALAM SATU TAHUN
C50: 1421 | E50: BEBAN DIBAYAR DI MUKA | W50: 2203 | Y50: UANG MUKA
C51: 1422 | E51: UANG MUKA | W51: 2228 | Y51: LIABILITAS JANGKA PENDEK LAINNYA
C52: 1423 | E52: PAJAK DIBAYAR DI MUKA | Y52: LIABILITAS JANGKA PANJANG
C53: 1499 | E53: ASET LANCAR LAINNYA | W53: 2301 | Y53: UTANG BANK JANGKA PANJANG
E54: ASET TIDAK LANCAR | W54: 2303 | Y54: UTANG JANGKA PANJANG - PIHAK KETIGA
C55: 1501 | E55: PIUTANG JANGKA PANJANG | W55: 2304 | Y55: UTANG JANGKA PANJANG - PIHAK YANG MEMPUNYAI HUBUNGAN ISTIMEWA
C56: 1523 | E56: TANAH DAN BANGUNAN | W56: 2321 | Y56: LIABILITAS PAJAK TANGGUHAN
C57: 1524 | E57: DIKURANGI: AKUMULASI PENYUSUTAN | W57: 2998 | Y57: LIABILITAS JANGKA PANJANG LAINNYA
C58: 1529 | E58: ASET TETAP LAINNYA | W58: 2999 | Y58: JUMLAH LIABILITAS
C59: 1530 | E59: DIKURANGI: AKUMULASI PENYUSUTAN | Y59: EKUITAS
C60: 1541 | E60: INVESTASI PADA PERUSAHAAN ASOSIASI | W60: 3102 | Y60: MODAL SAHAM
C61: 1599 | E61: INVESTASI JANGKA PANJANG LAINNYA | W61: 3120 | Y61: TAMBAHAN MODAL DISETOR
C62: 1600 | E62: ASET TAK BERWUJUD - NET | W62: 3200 | Y62: SALDO LABA
C63: 1611 | E63: ASET PAJAK TANGGUHAN | W63: 3298 | Y63: EKUITAS LAINNYA
C64: 1698 | E64: ASET TIDAK LANCAR LAINNYA | W64: 3200 | Y64: JUMLAH EKUITAS
C65: 1700 | E65: JUMLAH ASET | W65: 3300 | Y65: JUMLAH LIABILITAS DAN EKUITAS
D68: LAPORAN KEUANGAN | K68: DIAUDIT | O68: TIDAK DIAUDIT
D72: NPWP KANTOR AKUNTAN PUBLIK | X72: NPWP KONSULTAN PUBLIK
D75: NAMA KANTOR AKUNTAN PUBLIK | X75: NAMA KONSULTAN PUBLIK
AO79: HOME

Sheet L3A-3
B4: HOME | D4: PERHATIAN: | O4: REKONSILIASI LAPORAN KEUANGAN (INDUSTRI) | AH4: LAMPIRAN 3A-1
D5: LAMPIRAN INI HARUS DIISI OLEH WAJIB PAJAK YANG MENYELENGGARAKAN PEMBUKUAN STELSEL KAS ATAU PEMBUKUAN STELSEL AKRUAL DI SEKTOR USAHA INDUSTRI
N8: NIK/NPWP | AH8: TAHUN PAJAK | AL8: ='1'!E14 | AM8: ='1'!G14 | AN8: ='1'!I14 | AO8: ='1'!K14
C11: A.1 | D11: LAPORAN LABA RUGI
C13: KODE AKUN | E13: NAMA AKUN | K13: NILAI KOMERSIAL | O13: TIDAK TERMASUK OBJEK PAJAK | S13: DIKENAKAN PPh FINAL | W13: OBJEK PAJAK TIDAK FINAL | AA13: PENYESUAIAN FISKAL POSITIF | AE13: PENYESUAIAN FISKAL NEGATIF | AI13: KODE PENYESUAIAN FISKAL | AM13: NILAI FISKAL
C16: (1) | E16: (2) | K16: (3) | O16: (4) | S16: (5) | W16: (6) | AA16: (7) | AE16: (8) | AI16: (9) | AM16: (10)
E17: PENJUALAN
C18: 4002 | E18: PENJUALAN DOMESTIK
C19: 4003 | E19: PENJUALAN EKSPOR
C20: 4004 | E20: PENJUALAN BRUTO
E21: DIKURANGI:
C22: 4011 | E22: RETUR
C23: 4012 | E23: POTONGAN PENJUALAN
C24: 4020 | E24: PENJUALAN BERSIH
C25: 5040 | E25: BIAYA BAHAN BAKU
C26: 5050 | E26: BIAYA TENAGA KERJA LANGSUNG
E27: BIAYA PABRIKASI | AR27: FPO-01 | AS27: Biaya yang dibebankan/dikeluarkan untuk kepentingan pribadi Wajib Pajak atau orang yang menjadi tanggungannya
C28: 5051 | E28: BIAYA TENAGA KERJA TIDAK LANGSUNG | AR28: FPO-02 | AS28: Premi Asuransi kesehatan, asuransi kecelakaan, asuransi jiwa, asuransi dwiguna, dan asuransi beasiswa yang dibayar oleh Wajib Pajak
C29: 5052 | E29: BIAYA PEMELIHARAAN DAN PERBAIKAN MESIN | AR29: FPO-04 | AS29: Jumlah yang melebihi kewajaran yang dibayarkan kepada pihak yang mempunyai hubungan istimewa sehubungan dengan pekerjaan yang dilakukan
C30: 5058 | E30: BIAYA PENYUSUTAN DAN AMORTISASI | AR30: FPO-05 | AS30: Harta yang dihibahkan, bantuan atau sumbangan
C31: 5059 | E31: BIAYA UTILITAS | AR31: FPO-06 | AS31: Pajak penghasilan
C32: 5069 | E32: BIAYA PABRIKASI LAINNNYA | AR32: FPO-07 | AS32: Gaji yang dibayarkan kepada pemilik/orang yang menjadi tanggungannya
C33: 5070 | E33: JUMLAH BIAYA PABRIKASI | AR33: FPO-08 | AS33: Sanksi administrasi
C34: 5080 | E34: JUMLAH BIAYA PRODUKSI | AR34: FPO-09 | AS34: Selisih penyusutan komersial di atas penyusutan fiskal
C35: 5090 | E35: PERSEDIAAN AWAL BARANG DALAM PROSES | AR35: FPO-10 | AS35: Selisih amortisasi komersial di atas amortisasi fiskal
C36: 5099 | E36: DIKURANGI: PERSEDIAAN AKHIR BARANG DALAM PROSES | AR36: FPO-11 | AS36: Biaya untuk mendapatkan, menagih dan memelihara penghasilan yang dikenakan PPh Final dan penghasilan yang tidak termasuk objek pajak
C37: 5100 | E37: JUMLAH HARGA POKOK PRODUKSI | AR37: FPO-12 | AS37: Penyesuaian fiskal positif lainnya
C38: 5008 | E38: PERSEDIAAN AWAL BARANG JADI | AR38: FNE-01 | AS38: Penghasilan yang dikenakan PPh final dan penghasilan yang tidak termasuk objek pajak tetapi termasuk dalam peredaran usaha
C39: 5009 | E39: DIKURANGI: PERSEDIAAN AKHIR BARANG JADI | AR39: FNE-02 | AS39: Selisih penyusutan komersial di bawah penyusutan fiska
... C41: 4300 | E41: LABA KOTOR | AR41: FNE-04 | AS41: Penyesuaian fiskal negatif lainnya
E42: BEBAN USAHA
C43: 5311 | E43: BEBAN GAJI, TUNJANGAN, BONUS, HONORARIUM, THR, DLL
C44: 5313 | E44: BEBAN TRANSPORTASI
C45: 5314 | E45: BEBAN PENYUSUTAN DAN AMORTISASI
C46: 5315 | E46: BEBAN SEWA
C47: 5316 | E47: BEBAN BUNGA
C48: 5317 | E48: BEBAN SEHUBUNGAN DENGAN JASA
C49: 5318 | E49: BEBAN PIUTANG TIDAK TERTAGIH
C50: 5320 | E50: BEBAN PROMOSI/PEMASARAN
C51: 5321 | E51: BEBAN ENTERTAINMENT
C52: 5322 | E52: BEBAN UMUM DAN ADMINISTRASI
C53: 5399 | E53: BEBAN USAHA LAINNYA
C54: 5400 | E54: JUMLAH BEBAN USAHA
C55: 4800 | E55: LABA (RUGI) SEBELUM PAJAK
X56: PINDAHKAN LABA (RUGI) SEBELUM PAJAK KOLOM (10) KE INDUK BAGIAN B ANGKA 1 HURUF b
C57: A.2 | D57: LAPORAN POSISI KEUANGAN (NERACA)
C59: KODE AKUN | E59: AKUN | W59: KODE AKUN | Y59: AKUN
C61: (1) | E61: (2) | W61: (1) | Y61: (2)
E62: ASET LANCAR | Y62: LIABILITAS JANGKA PENDEK | AR62: HOME
C63: 1101 | E63: KAS DAN SETARA KAS | W63: 2102 | Y63: UTANG USAHA - PIHAK KETIGA
C64: 1200 | E64: INVESTASI | W64: 2103 | Y64: UTANG USAHA - PIHAK YANG MEMPUNYAI HUBUNGAN ISTIMEWA
C65: 1122 | E65: PIUTANG USAHA - PIHAK KETIGA | W65: 2111 | Y65: UTANG BANK
C66: 1123 | E66: PIUTANG USAHA - PIHAK YANG MEMPUNYAI HUBUNGAN ISTIMEWA | W66: 2191 | Y66: UTANG PAJAK
C67: 1124 | E67: PIUTANG LAINNYA - PIHAK KETIGA | W67: 2192 | Y67: UTANG DIVIDEN
C68: 1125 | E68: PIUTANG LAINNYA - PIHAK YANG MEMPUNYAI HUBUNGAN ISTIMEWA | W68: 2196 | Y68: BEBAN YANG MASIH HARUS DIBAYAR
C69: 1131 | E69: DIKURANGI: CADANGAN PIUTANG TAK TERTAGIH | W69: 2201 | Y69: UTANG BANK JANGKA PENDEK
C70: 1401 | E70: PERSEDIAAN | W70: 2202 | Y70: UTANG JANGKA PANJANG YANG JATUH TEMPO DALAM SATU TAHUN
C71: 1421 | E71: BEBAN DIBAYAR DI MUKA | W71: 2203 | Y71: UANG MUKA
C72: 1422 | E72: UANG MUKA | W72: 2228 | Y72: LIABILITAS JANGKA PENDEK LAINNYA
C73: 1423 | E73: PAJAK DIBAYAR DI MUKA | Y73: LIABILITAS JANGKA PANJANG
C74: 1499 | E74: ASET LANCAR LAINNYA | W74: 2301 | Y74: UTANG BANK JANGKA PANJANG
E75: ASET TIDAK LANCAR | W75: 2303 | Y75: UTANG JANGKA PANJANG - PIHAK KETIGA
C76: 1501 | E76: PIUTANG JANGKA PANJANG | W76: 2304 | Y76: UTANG JANGKA PANJANG - PIHAK YANG MEMPUNYAI HUBUNGAN ISTIMEWA
C77: 1523 | E77: TANAH DAN BANGUNAN | W77: 2321 | Y77: LIABILITAS PAJAK TANGGUHAN
C78: 1524 | E78: DIKURANGI: AKUMULASI PENYUSUTAN | W78: 2998 | Y78: LIABILITAS JANGKA PANJANG LAINNYA
C79: 1529 | E79: ASET TETAP LAINNYA | W79: 2999 | Y79: JUMLAH LIABILITAS
C80: 1530 | E80: DIKURANGI: AKUMULASI PENYUSUTAN | Y80: EKUITAS
C81: 1541 | E81: INVESTASI PADA PERUSAHAAN ASOSIASI | W81: 3102 | Y81: MODAL SAHAM
C82: 1599 | E82: INVESTASI JANGKA PANJANG LAINNYA | W82: 3120 | Y82: TAMBAHAN MODAL DISETOR
C83: 1600 | E83: ASET TAK BERWUJUD - NET | W83: 3200 | Y83: SALDO LABA
C84: 1611 | E84: ASET PAJAK TANGGUHAN | W84: 3298 | Y84: EKUITAS LAINNYA
C85: 1698 | E85: ASET TIDAK LANCAR LAINNYA | W85: 3200 | Y85: JUMLAH EKUITAS
C86: 1700 | E86: JUMLAH ASET | W86: 3300 | Y86: JUMLAH LIABILITAS DAN EKUITAS
D89: LAPORAN KEUANGAN | K89: DIAUDIT | O89: TIDAK DIAUDIT
D93: NPWP KANTOR AKUNTAN PUBLIK | X93: NPWP KONSULTAN PUBLIK
D96: NAMA KANTOR AKUNTAN PUBLIK | X96: NAMA KONSULTAN PUBLIK
AO100: HOME

Sheet L3A-4
B4: HOME | D4: PERHATIAN: | N4: A. | O4: PENGHASILAN NETO DALAM NEGERI DARI USAHA DAN/ATAU PEKERJAAN BEBAS BERDASARKAN PENCATATAN | AM4: LAMPIRAN 3A-4
D5: LAMPIRAN INI HARUS DIISI OLEH WAJIB PAJAK YANG MENYELENGGARAKAN PENCATATAN DAN/ATAU MEMILIKI PENGHASILAN NETO DALAM NEGERI LAINNYA
N6: B. | O6: PENGHASILAN NETO DALAM NEGERI LAINNYA
N8: NIK/NPWP | Q8: ='1'!J21 | R8: ='1'!K21 | S8: ='1'!L21 | T8: ='1'!M21 | U8: ='1'!N21 | V8: ='1'!O21 | W8: ='1'!P21 | X8: ='1'!Q21 | ... AF8: ='1'!Y21 | AM8: TAHUN PAJAK | AQ8: ='1'!E14 | AR8: ='1'!G14 | AS8: ='1'!I14 | AT8: ='1'!K14
C11: A. | D11: PENGHASILAN NETO DALAM NEGERI DARI USAHA DAN/ATAU PEKEJAAN BEBAS BERDASARKAN PENCATATAN
C13: NO. | D13: NAMA TEMPAT KEGIATAN USAHA (TKU) | L13: JENIS USAHA / PEKERJAAN BEBAS | T13: PEREDARAN BRUTO | AA13: NORMA (%) | AJ13: PENGHASILAN NETO | BH13: -
BH14: Dagang
C15: (1) | D15: (2) | L15: (3) | T15: (4) | AA15: (5) | AJ15: (6) | BH15: Industri
C16: 1 | L16: - | T16: =L3B!BJ75 -> 0 | AJ16: =T16*AA16 -> 0 | BH16: Jasa
BH17: Pengacara
B18: L3B bagian C | BH18: Akuntan
BH19: Konsultan
BH20: Aktuaris
BH21: Notaris/PPAT
BH22: Dokter
BH23: Penilai
BH24: Arsitek
BH25: Artis dan profesi sejenisnya
AV26: HOME | BH26: Pembuat konten
C27: JUMLAH TABEL A | R27: A | T27: =SUM(T16:T26) -> 0 | AH27: A.6 | AJ27: =SUM(AJ16:AJ26) -> 0 | BH27: Penulis
AD28: PINDAHKAN JUMLAH TABEL A.6 KE INDUK BAGIAN B ANGKA 1 HURUF b. | BH28: Olahragawan
C29: B. | D29: PENGHASILAN NETO DALAM NEGERI LAINNYA | BH29: Pelatih/Pengajar
BH30: Distributor perusahaan pemasaran berjenjang
C31: NO. | D31: KODE | K31: KODE | AE31: PENGHASILAN NETO | BH31: Agen iklan
BH32: Agen asuransi
C33: (1) | D33: (2) | K33: (3) | AE33: (4) | AW33: - | AX33: - | BH33: Perantara
C34: 1 | D34: - | K34: =VLOOKUP(D34,$AW$33:$AX$47,2,FALSE()) -> - | AW34: 302 | AX34: Sewa harta selain tanah dan/atau bangunan | BH34: Usaha/profesi Lainnya
C35: 2 | D35: - | K35: =VLOOKUP(D35,$AW$33:$AX$47,2,FALSE()) -> - | AW35: 304 | AX35: Bunga
C36: 3 | D36: - | K36: =VLOOKUP(D36,$AW$33:$AX$47,2,FALSE()) -> - | AW36: 306 | AX36: Royalti
C37: 4 | D37: - | K37: =VLOOKUP(D37,$AW$33:$AX$47,2,FALSE()) -> - | AW37: 307 | AX37: Keuntungan karena penjualan atau karena pengalihan harta
C38: 5 | D38: - | K38: =VLOOKUP(D38,$AW$33:$AX$47,2,FALSE()) -> - | AW38: 314 | AX38: Imbalan bunga
C39: 6 | D39: - | K39: =VLOOKUP(D39,$AW$33:$AX$47,2,FALSE()) -> - | AW39: 319 | AX39: Keuntungan selisih kurs mata uang asing
C40: 7 | D40: - | K40: =VLOOKUP(D40,$AW$33:$AX$47,2,FALSE()) -> - | AW40: 399 | AX40: Penghasilan lain dari modal atau aset
C41: 8 | D41: - | K41: =VLOOKUP(D41,$AW$33:$AX$47,2,FALSE()) -> - | AW41: 401 | AX41: Pembebasan utang\
C42: 9 | D42: - | K42: =VLOOKUP(D42,$AW$33:$AX$47,2,FALSE()) -> - | AW42: 402 | AX42: Hibah
C43: 10 | D43: - | K43: =VLOOKUP(D43,$AW$33:$AX$47,2,FALSE()) -> - | AW43: 403 | AX43: Bantuan/sumbangan
C44: 11 | D44: - | K44: =VLOOKUP(D44,$AW$33:$AX$47,2,FALSE()) -> - | AW44: 407 | AX44: Klaim asuransi
C45: 12 | D45: - | K45: =VLOOKUP(D45,$AW$33:$AX$47,2,FALSE()) -> - | AW45: 408 | AX45: Beasiswa
C46: 13 | D46: - | K46: =VLOOKUP(D46,$AW$33:$AX$47,2,FALSE()) -> - | AW46: 409 | AX46: Hadiah
C47: 14 | D47: - | K47: =VLOOKUP(D47,$AW$33:$AX$47,2,FALSE()) -> - | AW47: 412 | AX47: Penghasilan dalam negeri lainnya
C48: 15 | D48: - | K48: =VLOOKUP(D48,$AW$33:$AX$47,2,FALSE()) -> -
C49: 16 | D49: - | K49: =VLOOKUP(D49,$AW$33:$AX$47,2,FALSE()) -> -
C50: 17 | D50: - | K50: =VLOOKUP(D50,$AW$33:$AX$47,2,FALSE()) -> -
C51: 18 | D51: - | K51: =VLOOKUP(D51,$AW$33:$AX$47,2,FALSE()) -> -
C52: 19 | D52: - | K52: =VLOOKUP(D52,$AW$33:$AX$47,2,FALSE()) -> -
C53: 20 | D53: - | K53: =VLOOKUP(D53,$AW$33:$AX$47,2,FALSE()) -> -
C54: JUMLAH TABEL B | AC54: B | AE54: =SUM(AE34:AE53) -> 0
AD55: PINDAHKAN JUMLAH TABEL B KE INDUK BAGIAN B ANGKA 1 HURUF c.
AP56: HOME

Sheet L3B
D4: PERHATIAN: | R4: REKAPITULASI PEREDARAN BRUTO | BG4: LAMPIRAN 3B
D5: LAMPIRAN INI DIISI OLEH WAJIB PAJAK YANG BERKEWAJIBAN MELAPORKAN RINCIAN REKAPITULASI PEREDARAN BRUTO
AB8: NIK/NPWP | AE8: ='1'!J21 | AF8: ='1'!K21 | AG8: ='1'!L21 | AH8: ='1'!M21 | AI8: ='1'!N21 | AJ8: ='1'!O21 | AK8: ='1'!P21 | AL8: ='1'!Q21 | ... AT8: ='1'!Y21 | BG8: TAHUN PAJAK | BK8: ='1'!E14 | BL8: ='1'!G14 | BM8: ='1'!I14 | BN8: ='1'!K14
C11: DAFTAR TEMPAT KEGIATAN USAHA (TKU)
C13: NO. | E13: ID TKU | M13: NAMA TKU | W13: ALAMAT | AF13: KELURAHAN/DESA | AO13: KECAMATAN | AW13: KOTA/KABUPATEN | BF13: PROVINSI
C15: (1) | E15: (2) | M15: (3) | W15: (4) | AF15: (5) | AO15: (6) | AW15: (7) | BF15: (8)
C16: 1
C21: A. | D21: REKAPITULASI PEREDARAN BRUTO UNTUK WAJIB PAJAK ORANG PRIBADI YANG MEMILIKI PEREDARAN BRUTO TERTENTU YANG DIKENAI PAJAK BERSIFAT FINAL
C23: NO. | D23: NAMA TKU | N23: JANUARI | R23: FEBRUARI | V23: MARET | Z23: APRIL | AD23: MEI | AH23: JUNI | AL23: JULI | AP23: AGUSTUS | AT23: SEPTEMBER | AX23: OKTOBER | BB23: NOPEMBER | BF23: DESEMBER | BJ23: JUMLAH
C24: (1) | D24: (2) | N24: (3) | R24: (4) | V24: (5) | Z24: (6) | AD24: (7) | AH24: (8) | AL24: (9) | AP24: (10) | AT24: (11) | AX24: (12) | BB24: (13) | BF24: (14) | BJ24: (15)
C25: 1 | D25: =M16 | BJ25: =SUM(N25:BF25) -> 0
BJ26: =SUM(N26:BF26) -> 0
BJ27: =SUM(N27:BF27) -> 0
C28: a. | D28: JUMLAHPEREDARAN BRUTO | N28: =SUM(N25:N27) -> 0 | R28: =SUM(R25:R27) -> 0 | V28: =SUM(V25:V27) -> 0 | Z28: =SUM(Z25:Z27) -> 0 | AD28: =SUM(AD25:AD27) -> 0 | AH28: =SUM(AH25:AH27) -> 0 | AL28: =SUM(AL25:AL27) -> 0 | AP28: =SUM(AP25:AP27) -> 0 | AT28: =SUM(AT25:AT27) -> 0 | AX28: =SUM(AX25:AX27) -> 0 | BB28: =SUM(BB25:BB27) -> 0 | BF28: =SUM(BF25:BF27) -> 0 | BJ28: =SUM(BJ25:BJ27) -> 0
C30: b. | D30: AKUMULASI PEREDARAN BRUTO | N30: =N28 -> 0 | R30: =R28+N30 -> 0 | V30: =V28+R30 -> 0 | Z30: =Z28+V30 -> 0 | AD30: =AD28+Z30 -> 0 | AH30: =AH28+AD30 -> 0 | AL30: =AL28+AH30 -> 0 | AP30: =AP28+AL30 -> 0 | AT30: =AT28+AP30 -> 0 | AX30: =AX28+AT30 -> 0 | BB30: =BB28+AX30 -> 0 | BF30: =BF28+BB30 -> 0 | BJ30: =BF30 -> 0
C32: c. | D32: PEREDARAN BRUTO TIDAK KENA PAJAK | N32: 500000000 | BJ32: =N32 -> 500000000
C34: d. | D34: PEREDARAN BRUTO KENA PAJAK | N34: =IF(N30>=500000000,(N28-500000000),0) -> 0 | R34: =IF(R28<=500000000,IF(SUM(N28:U29)>500000000,R28,0),R28) -> 0 | V34: =IF(SUM(N28:U29)<=500000000,IF(SUM(N28:Y29)>500000000,(SUM(N28:Y29)-500000000),0),V28) -> 0 | Z34: =IF(SUM(N28:Y29)<=500000000,IF(SUM(N28:AC29)>500000000,(SUM(N28:AC29)-500000000),0),Z28) -> 0 | AD34: =IF(SUM(N28:AC29)<=500000000,IF(SUM(N28:AG29)>500000000,(SUM(N28:AG29)-500000000),0),AD28) -> 0 | AH34: =IF(SUM(N28:AG29)<=500000000,IF(SUM(N28:AK29)>500000000,(SUM(N28:AK29)-500000000),0),AH28) -> 0 | AL34: =IF(SUM(N28:AK29)<=500000000,IF(SUM(N28:AO29)>500000000,(SUM(N28:AO29)-500000000),0),AL28) -> 0 | AP34: =IF(SUM(N28:AO29)<=500000000,IF(SUM(N28:AS29)>500000000,(SUM(N28:AS29)-500000000),0),AP28) -> 0 | AT34: =IF(SUM(N28:AS29)<=500000000,IF(SUM(N28:AW29)>500000000,(SUM(N28:AW29)-500000000),0),AT28) -> 0 | AX34: =IF(SUM(N28:AW29)<=500000000,IF(SUM(N28:BA29)>500000000,(SUM(N28:BA29)-500000000),0),AX28) -> 0 | BB34: =IF(SUM(N28:BA29)<=500000000,IF(SUM(N28:BE29)>500000000,(SUM(N28:BE29)-500000000),0),BB28) -> 0 | BF34: =IF(SUM(N28:BE29)<=500000000,IF(SUM(N28:BI29)>500000000,(SUM(N28:BI29)-500000000),0),BF28) -> 0 | BJ34: =SUM(N34:BI35) -> 0
C36: e. | D36: JUMLAH PPh FINAL TERUTANG (0,5 % X d) | N36: =N34*0.5/100 -> 0 | R36: =R34*0.5/100 -> 0 | V36: =V34*0.5/100 -> 0 | Z36: =Z34*0.5/100 -> 0 | AD36: =AD34*0.5/100 -> 0 | AH36: =AH34*0.5/100 -> 0 | AL36: =AL34*0.5/100 -> 0 | AP36: =AP34*0.5/100 -> 0 | AT36: =AT34*0.5/100 -> 0 | AX36: =AX34*0.5/100 -> 0 | BB36: =BB34*0.5/100 -> 0 | BF36: =BF34*0.5/100 -> 0 | BJ36: =SUM(N36:BI37) -> 0
C38: f. | D38: JUMLAH PPh FINAL YANG DISETOR SENDIRI | N38: 0 | R38: 0 | V38: =V36 -> 0 | Z38: =Z36 -> 0 | AD38: =AD36 -> 0 | AH38: =AH36 -> 0 | AL38: =AL36 -> 0 | AP38: =AP36 -> 0 | AT38: =AT36 -> 0 | AX38: =AX36 -> 0 | BB38: =BB36 -> 0 | BF38: =BF36 -> 0 | BJ38: =SUM(N38:BI39) -> 0
C40: g. | D40: JUMLAH PPh FINAL YANG DIPOTONG/DIPUNGUT PIHAK LAIN | N40: 0 | R40: 0 | V40: 0 | Z40: 0 | AD40: 0 | AH40: 0 | AL40: 0 | AP40: 0 | AT40: 0 | AX40: 0 | BB40: 0 | BF40: 0 | BJ40: =SUM(N40:BI41) -> 0
C42: h. | D42: SELISIH (e - f - g ) | N42: =N36-N38-N40 -> 0 | R42: =R36-R38-R40 -> 0 | V42: =V36-V38-V40 -> 0 | Z42: =Z36-Z38-Z40 -> 0 | AD42: =AD36-AD38-AD40 -> 0 | AH42: =AH36-AH38-AH40 -> 0 | AL42: =AL36-AL38-AL40 -> 0 | AP42: =AP36-AP38-AP40 -> 0 | AT42: =AT36-AT38-AT40 -> 0 | AX42: =AX36-AX38-AX40 -> 0 | BB42: =BB36-BB38-BB40 -> 0 | BF42: =BF36-BF38-BF40 -> 0 | BJ42: =SUM(N42:BI43) -> 0
C44: i. | D44: SELSIH PADA SPT YANG DIBETULKAN | BJ44: =SUM(N44:BI45) -> 0
BP45: LAMPIRAN 2
C46: j. | D46: SELISIH KARENA PEMBETULAN (h - i) | BJ46: =SUM(N46:BI47) -> 0
D48: PINDAHKAN HURUF f JUMLAH PPh FINAL YANG DISETOR SENDIRI KOLOM (15) KE LAMPIRAN 2 BAGIAN A DENGAN KODE 28-423-99 JENIS PENGHASILAN "PENGHASILAN YANG DIKENAKAN PAJAK BERSIFAT FINAL SESUAI PERATURAN PEMERINTAH NOMOR 55 TAHUN 2022 (DISETOR SENDIRI)"
D50: PINDAHKAN HURUF g. JUMLAH PPh FINAL YANG DIPOTONG/DIPUNGUT PIHAK LAIN PADA KOLOM (3) SAMPAI (14) KE LAMPIRAN 2 BAGIAN A SESUAI DENGAN BUKTI PEMOTONGAN/PEMUNGUTAN PPh
C52: B. | D52: REKAPITULASI PEREDARAN BRUTO UNTUK WAJIB PAJAK ORANG PRIBADI PENGUSAHA TERTENTU (OPPT)
C54: METODE PEMBUKUAN | M54: 1. | N54: PENCATATAN | T54: 2. | U54: PEMBUKUAN STELSEL KAS ATAU PEMBUKUAN STELSEL AKRUAL
C56: NO. | D56: NAMA TKU | K56: METODE PEMBUKUAN | N56: JANUARI | R56: FEBRUARI | V56: MARET | Z56: APRIL | AD56: MEI | AH56: JUNI | AL56: JULI | AP56: AGUSTUS | AT56: SEPTEMBER | AX56: OKTOBER | BB56: NOVEMBER | BF56: DESEMBER | BJ56: JUMLAH
C58: (1) | D58: (2) | K58: (3) | N58: (4) | R58: (5) | V58: (6) | Z58: (7) | AD58: (8) | AH58: (9) | AL58: (10) | AP58: (11) | AT58: (12) | AX58: (13) | BB58: (14) | BF58: (15) | BJ58: (16)
BJ59: =SUM(N59:BF59) -> 0
BJ60: =SUM(N60:BF60) -> 0
BJ61: =SUM(N61:BF61) -> 0
C62: JUMLAH PEREDARAN BRUTO | N62: =SUM(N59:N61) -> 0 | R62: =SUM(R59:R61) -> 0 | V62: =SUM(V59:V61) -> 0 | Z62: =SUM(Z59:Z61) -> 0 | AD62: =SUM(AD59:AD61) -> 0 | AH62: =SUM(AH59:AH61) -> 0 | AL62: =SUM(AL59:AL61) -> 0 | AP62: =SUM(AP59:AP61) -> 0 | AT62: =SUM(AT59:AT61) -> 0 | AX62: =SUM(AX59:AX61) -> 0 | BB62: =SUM(BB59:BB61) -> 0 | BF62: =SUM(BF59:BF61) -> 0 | BJ62: =SUM(N62:BF62) -> 0 | BP62: HOME
C63: JUMLAH PPh | N63: =N62*0.75/100 -> 0 | R63: =R62*0.75/100 -> 0 | V63: =V62*0.75/100 -> 0 | Z63: =Z62*0.75/100 -> 0 | AD63: =AD62*0.75/100 -> 0 | AH63: =AH62*0.75/100 -> 0 | AL63: =AL62*0.75/100 -> 0 | AP63: =AP62*0.75/100 -> 0 | AT63: =AT62*0.75/100 -> 0 | AX63: =AX62*0.75/100 -> 0 | BB63: =BB62*0.75/100 -> 0 | BF63: =BF62*0.75/100 -> 0 | BJ63: =SUM(N63:BF63) -> 0
D64: JIKA METODE PEMBUKUAN ADALAH 1. PENCATATAN, PINDAHKAN SELURUH DATA PADA MASING-MASING TKU DARI KOLOM (1) SAMPAI KOLOM (16) PADA TABEL B KE TABEL C LAMPIRAN INI. BARIS JUMLAH PPh PADA KOLOM (4) SAMPAI DENGAN KOLOM (16) DIGABUNGKAN DENGAN JUMLAH PPh PADA TABEL C BARIS JUMLAH PPh SESUAI DENGAN KOLOM MASING-MASING.
D66: JIKA METODE PEMBUKUAN ADALAH 2. PEMBUKUAN STELSEL KAS ATAU PEMBUKUAN STELSEL AKRUAL, PINDAHKAN JUMLAH PEREDARAN BRUTO KOLOM (16) KE LAMPIRAN 3A-1/3A-2/3A-3 BAGIAN A.1. DAN JUMLAH PPh KOLOM (16) KE INDUK BAGIAN D ANGKA 10 HURUF b
C69: C. | D69: REKAPITULASI PEREDARAN BRUTO UNTUK PENGGUNA NORMA PENGHITUNGAN PENGHASILAN NETO (NPPN)
C71: NO. | D71: NAMA TKU | K71: JENIS USAHA/ PEKERJAAN BEBAS | N71: JANUARI | R71: FEBRUARI | V71: MARET | Z71: APRIL | AD71: MEI | AH71: JUNI | AL71: JULI | AP71: AGUSTUS | AT71: SEPTEMBER | AX71: OKTOBER | BB71: NOVEMBER | BF71: DESEMBER | BJ71: JUMLAH
C74: (1) | D74: (2) | K74: (3) | N74: (4) | R74: (5) | V74: (6) | Z74: (7) | AD74: (8) | AH74: (9) | AL74: (10) | AP74: (11) | AT74: (12) | AX74: (13) | BB74: (14) | BF74: (15) | BJ74: (16)
C75: 1 | BJ75: =SUM(N75:BF75) -> 0
BJ76: =SUM(N76:BF76) -> 0
BJ77: =SUM(N77:BF77) -> 0
C78: JUMLAH PEREDARAN BRUTO | N78: =SUM(N75:N77) -> 0 | R78: =SUM(R75:R77) -> 0 | V78: =SUM(V75:V77) -> 0 | Z78: =SUM(Z75:Z77) -> 0 | AD78: =SUM(AD75:AD77) -> 0 | AH78: =SUM(AH75:AH77) -> 0 | AL78: =SUM(AL75:AL77) -> 0 | AP78: =SUM(AP75:AP77) -> 0 | AT78: =SUM(AT75:AT77) -> 0 | AX78: =SUM(AX75:AX77) -> 0 | BB78: =SUM(BB75:BB77) -> 0 | BF78: =SUM(BF75:BF77) -> 0 | BJ78: =SUM(N78:BF78) -> 0 | BP78: L3A-4
C79: JUMLAH PPh | N79: 0 | R79: 0 | V79: 0 | Z79: 0 | AD79: 0 | AH79: 0 | AL79: 0 | AP79: 0 | AT79: 0 | AX79: 0 | BB79: 0 | BF79: 0 | BJ79: =SUM(N79:BF79) -> 0
R80: PINDAHKAN NAMA TKU KOLOM (2), JENIS USAHA/PEKERJAAN BEBAS KOLOM (3) DAN JUMLAH PEREDARAN BRUTO KOLOM (16) KE LAMPIRAN 3A-4 BAGIAN A DAN JUMLAH PPh KOLOM (16) KE INDUK BAGIAN D ANGKA 10 HUTUF b.

Sheet L3C
B4: HOME | D4: PERHATIAN: | X4: DAFTAR PENYUSUTAN DAN AMORTISASI FISKAL | AW4: LAMPIRAN 3C
D5: LAMPIRAN INI DIISI OLEH WAJIB PAJAK YANG MEMBEBANKAN BIAYA PENYUSUTAN DAN/ATAU AMORTISASI
W8: NIK/NPWP | AZ8: TAHUN PAJAK | BE8: ='1'!E14 | BF8: ='1'!G14 | BG8: ='1'!I14 | BH8: ='1'!K14
C11: A.1 | D11: LAPORAN LABA RUGI
C13: KODE HARTA | F13: KELOMPOK / JENIS HARGA | N13: BULAN / TAHUN PEROLEHAN | S13: HARGA PEROLEHAN (RUPIAH) | AA13: NILAI SISA BUKU FISKAL AWAL TAHUN (RUPIAH) | AI13: METODE PENYUSUTAN / AMORTISASI | AS13: PENYUSUTAN / AMORTISASI FISKAL PADA TAHUN INI (RUPIAH) | BB13: KETERANGAN | BK13: - | BL13: -
BK14: 0401 | BL14: Sepeda
AI15: KOMERSIAL | AN15: FISKAL | BK15: 0402 | BL15: Motor
C16: (1) | F16: (2) | N16: (3) | S16: (4) | AA16: (5) | AI16: (6) | AN16: (7) | AS16: (8) | BB16: (9) | BK16: 0403 | BL16: Mobil Penumpang
F17: I. | G17: HARTA BERWUJUD | BK17: 0404 | BL17: Bus
G18: A. | H18: KELOMPOK 1 | BK18: 0405 | BL18: Kendaraan Angkutan
H19: 1. | I19: …................................... | BK19: 0406 | BL19: Kendaraan Khusus
H20: 2. | I20: …................................... | BK20: 0407 | BL20: Kereta
H21: 3 | I21: …................................... | BK21: 0408 | BL21: Pesawat Terbang
G22: B. | H22: KELOMPOK 2 | BK22: 0409 | BL22: Kapal Laut
H23: 1. | I23: …................................... | BK23: 0410 | BL23: Mesin
H24: 2. | I24: …................................... | BK24: 0411 | BL24: Cart
H25: 3 | I25: …................................... | BK25: 0412 | BL25: Kapal Pesiar
G26: C. | H26: KELOMPOK 3 | BK26: 0413 | BL26: Peralatan
H27: 1. | I27: …................................... | BK27: 0499 | BL27: Aset Bergerak Lainnya
H28: 2. | I28: …................................... | BK28: 0707 | BL28: Peralatan Olahraga Khusus
H29: 3 | I29: …................................... | BK29: 0708 | BL29: Peralatan Elektronik
G30: D. | H30: KELOMPOK 4 | BK30: 0709 | BL30: Rumah Tangga/Furnitur
H31: 1. | I31: …................................... | BK31: 0710 | BL31: Peralatan Lainnya
H32: 2. | I32: …................................... | BK32: 0711 | BL32: Jet Ski
H33: 3 | I33: …................................... | BK33: 0799 | BL33: Aset Lainnya
G34: E. | H34: KELOMPOK LAINNYA | BK34: - | BL34: - | BX34: - | BY34: -
H35: 1. | I35: …................................... | BK35: Garis Lurus | BX35: 0502 | BY35: Bangunan untuk tempat tinggal
H36: 2. | I36: …................................... | BK36: Jumlah Angka Tahunan | BX36: 0503 | BY36: Bangunan untuk usaha (toko, pabrik, kantor, gudang dan sejenisnya)
H37: 3 | I37: …................................... | BK37: Saldo Menurun | BX37: 0504 | BY37: Bangunan yang disewakan
F38: II. | G38: BANGUNAN | BK38: Saldo Menurun Ganda | BX38: 0505 | BY38: Apartemen
G39: A. | H39: PERMANEN | BK39: Jumlah Jam Masa | BX39: 0599 | BY39: Aset tidak bergerak lainnya
H40: 1. | I40: …................................... | BK40: Jumlah Satuan Produksi
H41: 2. | I41: …................................... | BK41: Metode Lainnya
H42: 3 | I42: …................................... | BK42: - | BL42: -
G43: B. | H43: TIDAK PERMANEN | BK43: GL/Straight Line (Garis Lurus)
H44: 1. | I44: …................................... | BK44: JSP/Number of Production Unit (Jumlah Satuan Produksi)
H45: 2. | I45: …................................... | BK45: SM/Declining Method (Saldo Menurun)
C46: A. | D46: JUMLAH PENYUSUTAN FISKAL | BK46: - | BL46: -
C47: B. | D47: JUMLAH PENYUSUTAN KOMERSIAL | BK47: 0601 | BL47: Paten
C48: C. | D48: SELISIH PENYUSUTAN (A-B) | BK48: 0602 | BL48: Royalti
F49: III. | G49: HARTA TIDAK BERWUJUD | BK49: 0603 | BL49: Merek Dagang
G50: A. | H50: KELOMPOK 1 | BK50: 0604 | BL50: Hak Guna Bangunan
H51: 1. | I51: …................................... | BK51: 0605 | BL51: Hak Guna Usaha
G52: B. | H52: KELOMPOK 2 | BK52: 0606 | BL52: Hak Pakai
H53: 1. | I53: …................................... | BK53: 0607 | BL53: Niat Baik/Goodwill
G54: C. | H54: KELOMPOK 3 | BK54: 0608 | BL54: Hak Pengusahaan Hutan
H55: 1. | I55: …................................... | BK55: 0609 | BL55: Pengeluaran untuk Memperoleh Hak dan Pengeluaran Lain di Bidang Penambangan Minyak dan Gas Bumi
G56: D. | H56: KELOMPOK 4 | BK56: 0610 | BL56: Hak Pengusahaan Sumber Daya Alam dan Hasil Alam Lainnya
H57: 1. | I57: …................................... | BK57: 0699 | BL57: Harta Tidak Berwujud Lainnya
G58: E. | H58: KELOMPOK LAINNYA | BK58: - | BL58: -
H59: 1. | I59: …...................................
C60: D. | D60: JUMLAH AMORTISASI FISKAL
C61: E. | D61: JUMLAH AMORTISASI KOMERSIAL
C62: F. | D62: SELISIH AMORTISASI (D-E)
BG64: HOME

Sheet L3D
D4: PERHATIAN: | AM4: LAMPIRAN 3D
D5: LAMPIRAN INI DIISI OLEH WAJJIB PAJAK YANG MEMBEBANKAN BIAYA ENTERTAINMENT, BIAYA PROMOSI DAN PENJUALAN, SERTA PENGGANTIAN ATAU IMBALAN DALAM BENTUK NANTURA DAN/ATAU KENIKMATAN DAN/ATAU DAFTAR PIUTANG YANG NYATA-NYATA TIDAK DAPAT DITAGIH | N5: RINCIAN BIAYA TERTENTU
P10: NIK/NPWP | T10: ='1'!J21 | U10: ='1'!K21 | V10: ='1'!L21 | W10: ='1'!M21 | X10: ='1'!N21 | Y10: ='1'!O21 | Z10: ='1'!P21 | AA10: ='1'!Q21 | ... AI10: ='1'!Y21
AM11: TAHUN PAJAK | AQ11: ='1'!E14 | AR11: ='1'!G14 | AS11: ='1'!I14 | AT11: ='1'!K14
C14: A. | D14: DAFTAR NOMINATIF BIAYA ENTERTAINMENT
C16: NO. | E16: PEMBERIAN ENTERTAINMENT | AA16: RELASI USAHA YANG DIBERIKAN ENTERTAINMENT | AR16: KETERANGAN
E17: TANGGAL | H17: NAMA TEMPAT | N17: ALAMAT | S17: JENIS | W17: JUMLAH | AA17: NAMA | AE17: POSISI | AI17: NAMA PERUSAHAAN | AN17: JENIS USAHA
C18: (1) | E18: (2) | H18: (3) | N18: (4) | S18: (5) | W18: (6) | AA18: (7) | AE18: (8) | AI18: (9) | AN18: (10) | AR18: (11)
AW24: HOME
C28: B. | D28: DAFTAR NOMINATIF BIAYA PROMOSI SERTA PENGGANTIAN ATAU IMBALAN DALAM BENTUK NATURA DAN/ATAU KENIKMATAN
C30: NO. | E30: DATA PENERIMA | AK30: PEMOTONGAN/PEMUNGUTAN PPh
E31: NOMOR IDENTITAS | J31: NAMA | N31: ALAMAT | S31: TANGGAL | V31: BENTUK DAN JENIS BIAYA | AB31: NILAI | AF31: KETERANGAN | AK31: JUMLAH | AQ31: NOMOR BUKTI POTONG
C32: (1) | E32: (2) | J32: (3) | N32: (4) | S32: (5) | V32: (6) | AB32: (7) | AF32: (8) | AK32: (9) | AQ32: (10)
AW39: HOME
C42: C. | D42: DAFTAR PIUTANG YANG NYATA-NYATA TIDAK DAPAT DITAGIH
C44: NO. | E44: NOMOR IDENTITAS | K44: NAMA DEBITUR | P44: ALAMAT | U44: JUMLAH PLAFON PIUTANG | AA44: JUMLAH PIUTANG YANG NYATA-NYATA TIDAK DAPAT DITAGIH | AG44: METODE PEMBEBANAN | AM44: JENIS DOKUMEN PEMBUKTIAN PEMENUHAN PERSYARATAN
C47: (1) | E47: (2) | K47: (3) | P47: (4) | U47: (5) | AA47: (6) | AG47: (7) | AM47: (8)
AW48: -
AW49: Beban Langsung
AW50: Beban Cadangan
AW52: -
AW53: Penyerahan Perkara
AW54: Perjanjian Tertulis
AW55: Publikasi Penerbitan
AW56: Pengakuan Debitur
AQ57: HOME

Sheet L4
D4: PERHATIAN: | N4: A. | O4: PENGHITUNGAN ANGSURAN PPh PASAL 25 TAHUN PAJAK BERIKUTNYA | AM4: LAMPIRAN 4
D5: LAMPIRAN INI DIISI OLEH WAJIB PAJAK YANG BERKEWAJIBAN MEMBAYAR ANGSURAN PPh PASAL 25 DAN/ATAU WAJIB PAJAK YANG STATUS KEWAJIBAN PAJAK WAJIB PAJAK DAN PASANGANNYA ADALAH PISAH HARTA (PH) ATAU MEMILIH TERPISAH (MT) | N5: B. | O5: PENGHITUNGAN PPh TERUTANG WAJIB PAJAK DAN SUAMI/ISTRI
Q8: NIK/NPWP | T8: ='1'!J21 | U8: ='1'!K21 | V8: ='1'!L21 | W8: ='1'!M21 | X8: ='1'!N21 | Y8: ='1'!O21 | Z8: ='1'!P21 | AA8: ='1'!Q21 | ... AI8: ='1'!Y21
AM9: TAHUN PAJAK | AQ9: ='1'!E14 | AR9: ='1'!G14 | AS9: ='1'!I14 | AT9: ='1'!K14
C12: A. | D12: PENGHITUNGAN ANGSURAN PPh PASAL 25 TAHUN PAJAK BERIKUTNYA
D14: 1 | F14: PENGHASILAN NETO | AM14: ='1'!AL75 -> 0
D16: 2 | F16: KOMPENSASI KERUGIAN TAHUN PAJAK SEBELUMNYA | AM16: ='L5'!AZ30 -> 0
D18: 3 | F18: ZAKAT/SUMBANGAN KEAGAMAAN YANG BERSIFAT WAJIB | AM18: ='1'!AL77 -> 0
D20: 4 | F20: JUMLAH PENGHASILAN NETO | X20: ( | Y20: 1 | Z20: - | AA20: 2 | AB20: - | AC20: 3 | AD20: ) | AM20: =AM14-AM16-AM18 -> 0
AW21: - | AX21: 0
D22: 5 | F22: PENGHASILAN TIDAK KENA PAJAK | Y22: - | AM22: =VLOOKUP(Y22,AW21:AX33,2,FALSE()) -> 0 | AW22: TK/0 | AX22: 54000000
AW23: TK/1 | AX23: 58500000
D24: 6 | F24: PENGHASILAN KENA PAJAK | X24: ( | Y24: 4 | Z24: - | AA24: 5 | AB24: ) | AM24: =AM20-AM22 -> 0 | AW24: TK/2 | AX24: 63000000
AW25: TK/3 | AX25: 67500000
D26: 7 | F26: PPh TERUTANG | AM26: =(5%*60000000)+(15%*190000000)+(25%*(267000000-250000000)) -> 35750000 | AW26: K/0 | AX26: 58500000
AW27: K/1 | AX27: 63000000
D28: 8 | F28: PENGURANG PPh TERUTANG | AM28: 0 | AW28: K/2 | AX28: 67500000
AW29: K/3 | AX29: 72000000
D30: 9 | F30: KREDIT PAJAK | AM30: ='1'!AL98 -> 0 | AW30: K/I/0 | AX30: 112500000
AW31: K/I/1 | AX31: 117000000
D32: 10 | F32: PPh YANG HARUS DIBAYAR | X32: ( | Y32: 7 | Z32: - | AA32: 8 | AB32: - | AC32: 9 | AD32: ) | AM32: =AM26-AM28-AM30 -> 35750000 | AW32: K/I/2 | AX32: 121500000
AW33: K/I/3 | AX33: 126000000
D34: 11 | F34: ANGSURAN PPh PASAL 25 TAHUN PAJAK BERIKUTNYA | X34: ( | Y34: 1/12 | AA34: X | AC34: 10 | AD34: ) | AM34: =1/12*AM32 -> 2979166.7
R37: PINDAHKAN JUMLAH ANGSURAN PPh PASAL 25 TAHUN PAJAK BERIKUTNYA PADA NOMOR 11 KE INDUK BAGIAN H ANGKA 13 HURUF b
C39: B. | D39: PENGHITUNGAN PPh TERUTANG WAJIB PAJAK DAN SUAMI/ISTRI
AH41: WAJIB PAJAK | AO41: SUAMI/ISTRI
D43: 1 | F43: PENGHASILAN BRUTO
D45: 2 | F45: PENGHASILAN NETO
D47: 3 | F47: PENGHASILAN NETO SETELAH DIKURANGI ZAKAT/SUMBANGAN KEAGAMAAN WAJIB DAN KOMPENSASI KERUGIAN | AG47: 3a | AN47: 3b
D49: 4 | F49: PENGHASILAN NETO SETELAH DIKURANGI ZAKAT/SUMBANGAN KEAGAMAAN WAJIB DAN KOMPENSASI KERUGIAN GABUNGAN | AG49: =AH47+AO47 -> 0
D51: 5 | F51: PENGHASILAN TIDAK KENA PAJAK GABUNGAN | Y51: K/I/0
D53: 6 | F53: PENGHASILAN KENA PAJAK GABUNGAN | Y53: ( | Z53: 4 | AA53: - | AB53: 5 | AC53: ) | AG53: =AG49-AG51 -> 0
D55: 7 | F55: PPh TERUTANG GABUNGAN
D57: 8 | F57: PPh TERUTANG YANG DI TANGGUNG WAJIB PAJAK | W57: {[ | X57: 3a | Y57: : | Z57: 4 | AA57: ] | AB57: X | AC57: 7 | AD57: } | AG57: =(AH47/AG49)*AG55 -> #DIV/0!
D59: 9 | F59: PPh TERUTANG YANG DITANGGUNG OLEH SUAMI/ISTRI | W59: {[ | X59: 3b | Y59: : | Z59: 4 | AA59: ] | AB59: X | AC59: 7 | AD59: } | AG59: =(AO47/AG49)*AG55 -> #DIV/0!
P64: PINDAHKAN JUMLAH PPh TERUTANG YANG DITANGGUNG OLEH WAJIB PAJAK PADA NOMOR 8 KE INDUK BAGIAN C ANGKA 7 SPT WAJIB PAJAK
P65: PINDAHKAN JUMLAH PPh TERUTANG YANG DITANGGUNG OLEH SUAMI/ISTRI PADA NOMOR 9 KE INDUK BAGIAN C ANGKA 7 SPT SUAMI/ISTRI
D67: WAJIB PAJAK
AE69: NAMA DAN TTD
D70: NIK/NPWP
D72: NAMA
D76: SUAMI/ISTRI
AE78: NAMA DAN TTD
D79: NIK/NPWP
D81: NAMA
AQ85: HOME

Sheet L5
D4: PERHATIAN: | W4: A. | X4: PENGHITUNGAN KOMPENSASI KERUGIAN FISKAL | AZ4: LAMPIRAN 5
D5: LAMPIRAN INI DIISI OLEH WAJIB PAJAK YANG MENGAKUI KOMPENSASI KERUGIAN FISKAL,PENGURANG PENGHASILAN NETO, DAN/ATAU PENGURANG PPh TERUTANG | W5: B. | X5: PENGURANG PENGHASILAN NETO
W6: C. | X6: PENGURANG PPh TERUTANG
W8: NIK/NPWP | Z8: ='1'!J21 | AA8: ='1'!K21 | AB8: ='1'!L21 | AC8: ='1'!M21 | AD8: ='1'!N21 | AE8: ='1'!O21 | AF8: ='1'!P21 | AG8: ='1'!Q21 | ... AO8: ='1'!Y21 | AZ8: TAHUN PAJAK | BD8: ='1'!E14 | BE8: ='1'!G14 | BF8: ='1'!I14 | BG8: ='1'!K14
C11: A. | D11: PENGHITUNGAN KOMPENSASI KERUGIAN FISKAL
C13: NO. | D13: LABA/RUGI NETO FISKAL | L13: KOMPENSASI KERUGIAN FISKAL
M15: TAHUN | O15: 2 | P15: 0 | Q15: 2 | R15: 1 | U15: TAHUN | W15: 2 | X15: 0 | Y15: 2 | Z15: 2 | AC15: TAHUN | AE15: 2 | AF15: 0 | AG15: 2 | AH15: 3 | AK15: TAHUN | AM15: 2 | AN15: 0 | AO15: 2 | AP15: 4 | AS15: TAHUN | AU15: 2 | AV15: 0 | AW15: 2 | AX15: 5 | BA15: TAHUN | BC15: 2 | BD15: 0 | BE15: 2 | BF15: 6
D16: TAHUN PAJAK | H16: RUPIAH
L17: RUPIAH | T17: RUPIAH | AB17: RUPIAH | AJ17: RUPIAH | AR17: RUPIAH | AZ17: RUPIAH
AR18: (TAHUN PAJAK INI) | AZ18: (TAHUN PAJAK BERJALAN)
C19: (1) | D19: (2) | H19: (3) | L19: (4) | T19: (5) | AB19: (6) | AJ19: (7) | AR19: (8) | AZ19: (9)
C20: 1 | L20: 0 | T20: 0 | AB20: 0 | AJ20: 0 | AR20: 0
C21: 2 | L21: 0 | T21: 0 | AB21: 0 | AJ21: 0 | AR21: 0
C22: 3 | L22: 0 | T22: 0 | AB22: 0 | AJ22: 0 | AR22: 0 | AZ22: 0
C23: 4 | L23: 0 | T23: 0 | AB23: 0 | AJ23: 0 | AR23: 0
C24: 5 | L24: 0 | T24: 0 | AB24: 0 | AJ24: 0 | AR24: 0
C25: 6 | L25: 0 | T25: 0 | AB25: 0 | AJ25: 0 | AR25: 0
C26: 7
C27: 8
C28: 9
C29: 10
C30: JUMLAH TABEL A | J30: A | L30: =SUM(L20:L29) -> 0 | T30: =SUM(T20:T29) -> 0 | AB30: =SUM(AB20:AB29) -> 0 | AJ30: =SUM(AJ20:AJ29) -> 0 | AR30: =SUM(AR20:AR29) -> 0 | AZ30: =SUM(AZ20:AZ29) -> 0
AJ31: PINDAHKAN JUMLAH TABEL A KOLOM (8) KE LAMPIRAN INI BAGIAN B BARIS 6 KOLOM (4)
C33: B. | D33: PENGURANG PENGHASILAN BRUTO | AB33: C. | AC33: PENGURANG PPh TERUTANG
C35: NO. | D35: KODE | I35: JENIS PENGURANG PENGHASILAN NETO | R35: JUMLAH PENGURANG PENGHASILAN NETO | AB35: NO. | AC35: KODE | AH35: JENIS PENGURANG PPh TERUTANG | AQ35: JUMLAH PENGURANG PPh TERUTANG
A37: - | B37: - | C37: (1) | D37: (2) | I37: (3) | R37: (4) | AB37: (1) | AC37: (2) | AH37: (3) | AQ37: (4) | AZ37: - | BA37: -
A38: 501 | B38: Zakat | C38: 1 | D38: - | I38: =VLOOKUP(D38,$A$37:$B$42,2,FALSE()) -> - | AB38: 1 | AC38: - | AH38: =VLOOKUP(AC38,$AZ$37:$BA$39,2,FALSE()) -> - | AQ38: 0 | AZ38: 506 | BA38: Fasilitas pembebasan atau pengurang PPh (Tax Holiday)
A39: 502 | B39: Sumbangan Keagamaan | C39: 2 | D39: - | I39: =VLOOKUP(D39,$A$37:$B$42,2,FALSE()) -> - | AB39: 2 | AC39: - | AH39: =VLOOKUP(AC39,$AZ$37:$BA$39,2,FALSE()) -> - | AQ39: 0 | AZ39: 505 | BA39: Pengurang PPh Lainnya
A40: 503 | B40: Fasilitas Pengurang Penghasilan Kena Pajak (Tax Allowance) | C40: 3 | D40: - | I40: =VLOOKUP(D40,$A$37:$B$42,2,FALSE()) -> - | AB40: 3 | AC40: - | AH40: =VLOOKUP(AC40,$AZ$37:$BA$39,2,FALSE()) -> - | AQ40: 0
A41: 504 | B41: Fasilitas keringanan pajak lainnya (Tax Reliefs) | C41: 4 | D41: - | I41: =VLOOKUP(D41,$A$37:$B$42,2,FALSE()) -> - | AB41: 4 | AC41: - | AH41: =VLOOKUP(AC41,$AZ$37:$BA$39,2,FALSE()) -> - | AQ41: 0
A42: 505 | B42: Pengurang Penghasilan Neto Lainnya | C42: 5 | D42: JUMLAH TABEL B | P42: B.5 | R42: =SUM(R38:R41) -> 0 | AB42: 5 | AC42: - | AH42: =VLOOKUP(AC42,$AZ$37:$BA$39,2,FALSE()) -> - | AQ42: 0
C43: 6 | D43: JUMLAH KOMPENSASI KERUGIAN FISKAL | P43: B.6 | R43: =AR30 -> 0 | AB43: 6 | AC43: - | AH43: =VLOOKUP(AC43,$AZ$37:$BA$39,2,FALSE()) -> - | AQ43: 0
C44: 7 | D44: JUMLAH PENGURANG PENGHASILAN NETO (B.5 + B.6) | P44: B.7 | R44: =R42+R43 -> 0 | AB44: 7 | AC44: JUMLAH TABEL C | AO44: C | AQ44: =SUM(AQ38:AQ43) -> 0
C45: PINDAHKAN JUMLAH PENGURANG PENGHASILAN NETO (B.7) DI BARIS 7 KOLOM (4) KE INDUK BAGIAN C ANGKA 3
AU46: HOME

Sheet Sheet1
B3: Imbalan kepada Bukan Pegawai Lainnya yang mendapat fasilitas di daerah tertentu
B4: Upah Pegawai Tidak Tetap yang Dibayarkan secara Harian, Mingguan, Satuan dan Borongan dengan Penghasilan Bruto sampai dengan Rp2.500.000 Sehari yang Mendapat Fasilitas di Daerah Tertentu
B5: Upah Pegawai Tidak Tetap yang Dibayarkan secara Harian, Mingguan, Satuan dan Borongan dengan Penghasilan Bruto lebih dari Rp2.500.000 Sehari yang Mendapat Fasilitas di Daerah Tertentu
B6: Penghasilan yang Diterima atau Diperoleh Pegawai Tetap yang Menerima Fasilitas di Daerah Tertentu
B7: Uang Pesangon yang Dibayarkan Sekaligus
B8: Uang Manfaat Pensiun, Tunjangan Hari Tua atau Jaminan Hari Tua dan Pembayaran Sejenis yang Dibayarkan Sekaligus
B9: Honor dan Imbalan Lain yang Dibebankan Dibebankan kepada APBN atau APBD yang Diterima oleh PNS, Anggota TNI/POLRI, Pejabat Negara dan Pensiunannya (LAMA)
B10: Honor atau Imbalan Lain yang Dibebankan kepada APBN atau APBD yang Diterima oleh PNS Golongan III, Anggota TNI dan Anggota POLRI Golongan Pangkat Perwira Pertama, dan pensiunannya
B11: Honor atau Imbalan Lain yang Dibebankan kepada APBN atau APBD yang Diterima oleh Pejabat Negara, PNS Golongan IV, Anggota TNI dan Anggota POLRI Golongan Pangkat Perwira Menengah dan Perwira Tinggi, dan Pensiunannya
B12: Honor atau Imbalan Lain yang Dibebankan kepada APBN atau APBD yang Diterima oleh PNS Golongan I dan Golongan II, Anggota TNI dan Anggota POLRI Golongan Pangkat Tamtama dan Bintara, dan Pensiunannya
B13: Objek PPh Pasal 21 yang Bersifat Final Lainnya
B14: Penghasilan Sehubungan dengan Transaksi Penjualan Barang, Penyerahan Jasa, dan/atau Persewaan serta Penghasilan Lain Sehubungan dengan Penggunaan Harta yang Dilakukan Melalui Pihak Lain dalam Sistem Informasi Pengadaan Pemerintah (Final)
... B101: Penghasilan Final Lainnya
